Workbook

Sheet README
A1: Hyde Park BESS (Project 21334 / 24211) - Cost Analysis Workbook
A3: Purpose | B3: Traceable data source behind the Cost Analysis deck, Basis of Estimate and all-in cost whitepaper. Every number on a slide ties to a cell here.
A4: Prepared | B4: Eversource Cost Estimating CoE, 29 Sep 2026. Source of record: ESF - Hyde Park BESS Total Rev 3.xlsm (24 Sep 2026), Item and Overview tabs.
A5: Convention | B5: Blue font = input value keyed from a source document (editable). Black = formula. Navy header = section. Gold fill = headline metric.
A6: Tab: Layers | B6: Rev 3 line items rolled into 13 cost layers (A-M). Directs are as-estimated; the 'Loaded' column spreads Station 360 risk, contingency, indirects and AFUDC pro rata over direct layers so each layer carries its full share of the approval-level total.
A7: Tab: Unit Costs | B7: $/kW and $/kWh at each boundary: vendor contract only, battery system installed, station complete, all-in approval level, and all-in including the D-Line interconnection (24211).
A8: Tab: Timeline | B8: Every funding action, estimate and vendor price point from the 2021 IFR to Rev 3, with basis and in-service date drift.
A9: Tab: Sept 2026 Walk | B9: Rev 0 -> Rev 1 -> Rev 2 -> Rev 3 variance walk from the ESF revisions and the 9/1-9/23/2026 email record.
A10: Tab: Benchmarks | B10: Published industry benchmarks with metric definition, dollar year and duration. Source quality tier: green = primary, yellow = secondary.
A11: Tab: 2023 Indicative | B11: July 2023 five-bidder indicative pricing (Site Two = Hyde Park 10 MW/20 MWh) and what each excluded.
A12: Tab: Line Items | B12: All 292 Rev 3 line items with the layer assignment used for the roll-up. Change a layer letter in column K and the Layers tab recalculates.
A13: Vintage / escalation | B13: Rev 3 carries $2,948,100 of escalation (ESF Overview). Battery line escalated at 3%/yr to 2027-28 delivery even though the Nomad price is fixed until Final Acceptance; see BOE section 'Escalation'.
A14: Accuracy | B14: Rev 3 is classed Conceptual (-25% / +50%) on the ESF. Sta 360 preliminary engineering is in progress (Sep 2026); IFC expected Aug 2027.
... A18: 2026$ Adjustment | B18: Dollar-year adjustment of the 13 reference-class comparables to 2026 under three battery indices (selector in B6), battery-share and escalation inputs, medians and Hyde Park percentiles; New York distribution-scale cohort (NineDot, Elevate, Soltage, NYSERDA averages, Con Edison interconnection). Deck slides 12-13. Added 2 Oct 2026.

Sheet Layers
A1: Cost layers - ESF Total Rev 3 (24 Sep 2026), Project 21334 (Sta 360 + Sta 496)
A2: Directs by layer are SUMIFS over the Line Items tab. Loaded = Station 360 direct layers x load factor (risk + contingency + indirects + AFUDC spread pro rata); Station 496 is carried whole as an interconnection cost.
A4: Layer | B4: Direct ($) | C4: % of total | D4: Loaded ($) | E4: % of loaded | F4: Cumulative loaded ($) | G4: What it is
A5: A. Battery supply contract (Nomad) | B5: =SUMIFS('Line Items'!$H:$H,'Line Items'!$L:$L,"A") -> 12991104 | C5: =B5/$B$18 -> 0.22692858 | D5: =B5*$B$21 -> 21893672 | E5: =D5/$D$18 -> 0.38243863 | F5: =SUM($D$5:D5) -> 21893672 | G5: Nomad fixed-price supply contract $12,106,850 (12 Voyager 3.0 LFP units, PCS, BMS, fire protection, 10-yr warranty, spares, remote support) as carried in Rev 3: $1,213,043 actual LNTP payments + $11,778,062 to-go (escalated).
A6: B. Battery installation & integration (owner scope) | B6: =SUMIFS('Line Items'!$H:$H,'Line Items'!$L:$L,"B") -> 1733346.5 | C6: =B6/$B$18 -> 0.030278093 | D6: =B6*$B$21 -> 2921177.4 | E6: =D6/$D$18 -> 0.051027122 | F6: =SUM($D$5:D6) -> 24814849 | G6: Owner-scope work that exists only because of the batteries: 5,557 mh installation labor, 12 foundation pads, fire suppression, GSU-to-BESS conduit and 600 V cable.
A7: C. Battery balance-of-plant (GSUs, EMS/comms, aux power) | B7: =SUMIFS('Line Items'!$H:$H,'Line Items'!$L:$L,"C") -> 1932801.6 | C7: =B7/$B$18 -> 0.033762175 | D7: =B7*$B$21 -> 3257315.5 | E7: =D7/$D$18 -> 0.056898782 | F7: =SUM($D$5:D7) -> 28072165 | G7: Four 3 MVA 13.8 kV/480 V generator step-up transformers, site EMS/communications, AC/DC auxiliary power panels. Vendors often bundle these in a 'turnkey' quote; here they are owner-furnished.
A8: D. Station 360 13.8 kV switching & interconnection facilities | B8: =SUMIFS('Line Items'!$H:$H,'Line Items'!$L:$L,"D") -> 3846444.3 | C8: =B8/$B$18 -> 0.067189683 | D8: =B8*$B$21 -> 6482343 | E8: =D8/$D$18 -> 0.11323356 | F8: =SUM($D$5:D8) -> 34554508 | G8: The new 13.8 kV switching station (Sta 360): four Siemens SDV7 1200 A breaker skids with relays/PTs/DC, disconnects, metering transclosures, station service transformer, riser poles, 15 kV cable, duct bank to feeder manholes, ground grid, lighting, control cable.
A9: E. Site development & civil (former landfill site) | B9: =SUMIFS('Line Items'!$H:$H,'Line Items'!$L:$L,"E") -> 2690784.1 | C9: =B9/$B$18 -> 0.047002613 | D9: =B9*$B$21 -> 4534729.8 | E9: =D9/$D$18 -> 0.079212652 | F9: =SUM($D$5:D9) -> 39089238 | G9: Developing a 200 ft x 200 ft yard on a closed construction-debris landfill: clear and grub, 760 ft access road, 24+12 soil borings, 2,520 CY cut, imported fill, trap rock, 14 ft retaining wall, fence, mob/demob.
A10: F. Station 496 feeder protection upgrades (interconnection) | B10: =SUMIFS('Line Items'!$H:$H,'Line Items'!$L:$L,"F") -> 7253161.7 | C10: =B10/$B$18 -> 0.12669822 | D10: =B10 -> 7253161.7 | E10: =D10/$D$18 -> 0.12669822 | F10: =SUM($D$5:D10) -> 46342399 | G10: Station 496 protection upgrades required to accept the BESS on four feeders: 20 SEL relays, transfer trip over dark fiber, RTU/SCADA points, removals. Carried at its full approval level incl. its own indirects/AFUDC/contingency.
A11: G. Testing & commissioning | B11: =SUMIFS('Line Items'!$H:$H,'Line Items'!$L:$L,"G") -> 1262913.6 | C11: =B11/$B$18 -> 0.022060573 | D11: =B11*$B$21 -> 2128365.4 | E11: =D11/$D$18 -> 0.037178284 | F11: =SUM($D$5:D11) -> 48470765 | G11: Lead commissioning engineer, field test engineers, field SCADA and telecom commissioning.
A12: H. Owner soft costs (engineering, siting, environmental, outreach, PM, land) | B12: =SUMIFS('Line Items'!$H:$H,'Line Items'!$L:$L,"H") -> 4420366.5 | C12: =B12/$B$18 -> 0.077214954 | D12: =B12*$B$21 -> 7449563.6 | E12: =D12/$D$18 -> 0.13012896 | F12: =SUM($D$5:D12) -> 55920328 | G12: Engineering (internal and Leidos/VHB), Article 80 siting and legal, environmental permits (DEP post-closure use, SWPPP, Tier II), community outreach, project management, construction reps, land.
A13: I. Taxes, CWIP, builders-risk insurance | B13: =SUMIFS('Line Items'!$H:$H,'Line Items'!$L:$L,"I") -> 787533.21 | C13: =B13/$B$18 -> 0.013756629 | D13: =B13*$B$21 -> 1327215.5 | E13: =D13/$D$18 -> 0.023183797 | F13: =SUM($D$5:D13) -> 57247544 | G13: Property tax, CWIP, sales and use tax on external material, builders all-risk insurance.
A14: J. Risk register | B14: =SUMIFS('Line Items'!$H:$H,'Line Items'!$L:$L,"J") -> 5300000 | C14: =B14/$B$18 -> 0.092580391 | D14: 0 | E14: =D14/$D$18 -> 0 | F14: =SUM($D$5:D14) -> 57247544 | G14: Twelve enumerated risk items on Sta 360 (see BOE).
A15: K. Contingency | B15: =SUMIFS('Line Items'!$H:$H,'Line Items'!$L:$L,"K") -> 2283517 | C15: =B15/$B$18 -> 0.039888471 | D15: 0 | E15: =D15/$D$18 -> 0 | F15: =SUM($D$5:D15) -> 57247544 | G15: General contingency on Sta 360.
A16: L. Indirects / overheads | B16: =SUMIFS('Line Items'!$H:$H,'Line Items'!$L:$L,"L") -> 8064672.4 | C16: =B16/$B$18 -> 0.14087368 | D16: 0 | E16: =D16/$D$18 -> 0 | F16: =SUM($D$5:D16) -> 57247544 | G16: Corporate indirects: E&S station overhead, general services, non-productive time, payroll benefits, AS&E, MDEC, vehicles, lobby stock.
A17: M. AFUDC | B17: =SUMIFS('Line Items'!$H:$H,'Line Items'!$L:$L,"M") -> 4680899.2 | C17: =B17/$B$18 -> 0.081765939 | D17: 0 | E17: =D17/$D$18 -> 0 | F17: =SUM($D$5:D17) -> 57247544 | G17: Allowance for funds used during construction, Sta 360.
A18: Total - Project 21334 approval level | B18: =SUM(B5:B17) -> 57247544 | C18: =SUM(C5:C17) -> 1 | D18: =SUM(D5:D17) -> 57247544 | E18: =SUM(E5:E17) -> 1
A20: Station 360 direct layers A-E, G-I (sum) | B20: =SUMPRODUCT(--(LEFT(A5:A17,1)<>"F"),--(LEFT(A5:A17,1)<>"J"),--(LEFT(A5:A17,1)<>"K"),--(LEFT(A5:A17,1)<>"L"),--(LEFT(A5:A17,1)<>"M"),B5:B17) -> 29665294
A21: Load factor = (Sta 360 directs + J+K+L+M) / Sta 360 directs | B21: =(B20+B14+B15+B16+B17)/B20 -> 1.6852819
A22: Check: loaded total less direct total (should be 0) | B22: =D18-B18 -> 0
A24: Memo: D-Line interconnection, project 24211 (SSF Feb 2024 conceptual, not re-estimated) | B24: 4793000
A25: Memo: Nomad contract fixed price (Exhibit C, cover agreement dated 3/10/2026) | B25: 12106850
A26: Memo: escalation carried on the fixed-price battery line (Rev 3 line 432 less contract balance) | B26: =11778061.83-(11860850-1213042.82) -> 1130254.6

Sheet Unit Costs
A1: Unit costs at each cost boundary (10 MW / 20 MWh, 2-hour)
A3: Nameplate MW | B3: 10
A4: Nameplate MWh | B4: 20
A6: Boundary | B6: Total ($) | C6: $/kW | D6: $/kWh | E6: Multiple of vendor contract | F6: Definition
A7: 1. Vendor contract as quoted (Nomad fixed price) | B7: =Layers!B25 -> 12106850 | C7: =B7/($B$3*1000) -> 1210.685 | D7: =B7/($B$4*1000) -> 605.3425 | E7: =B7/$B$7 -> 1 | F7: What the vendor calls 'the project cost': containers, batteries, PCS, BMS, fire protection, spares, 7-yr warranty extension, remote support, shipping, supervision, commissioning, training.
A8: 2. Battery supply as carried in Rev 3 (contract + actuals + escalation) - Layer A | B8: =Layers!B5 -> 12991104 | C8: =B8/($B$3*1000) -> 1299.1104 | D8: =B8/($B$4*1000) -> 649.55519 | E8: =B8/$B$7 -> 1.0730375 | F8: Rev 3 line 432 + line 445.
A9: 3. Battery system installed (Layers A+B+C, direct) | B9: =SUM(Layers!B5:B7) -> 16657252 | C9: =B9/($B$3*1000) -> 1665.7252 | D9: =B9/($B$4*1000) -> 832.86259 | E9: =B9/$B$7 -> 1.3758535 | F9: Adds owner installation labor, pads, fire suppression, GSUs, EMS/comms, aux power. Closest analogue to a 'turnkey BESS' benchmark before soft costs.
A10: 4. Station complete, direct (Layers A-E + G-I, no loaders) | B10: =Layers!B20 -> 29665294 | C10: =B10/($B$3*1000) -> 2966.5294 | D10: =B10/($B$4*1000) -> 1483.2647 | E10: =B10/$B$7 -> 2.45029 | F10: Adds the 13.8 kV switching station, landfill site development, testing, owner soft costs and taxes.
A11: 5. Station 360 approval level (loaded) | B11: =SUM(Layers!D5:D9)+SUM(Layers!D11:D13) -> 49994382 | C11: =B11/($B$3*1000) -> 4999.4382 | D11: =B11/($B$4*1000) -> 2499.7191 | E11: =B11/$B$7 -> 4.1294294 | F11: Adds risk, contingency, indirects and AFUDC. Equals ESF 'Hyde Park BESS - Sta. 360 - Rev 3' $49,994,200.
A12: 6. Project 21334 approval level (Sta 360 + Sta 496) | B12: =Layers!D18 -> 57247544 | C12: =B12/($B$3*1000) -> 5724.7544 | D12: =B12/($B$4*1000) -> 2862.3772 | E12: =B12/$B$7 -> 4.7285251 | F12: Adds the Station 496 feeder protection upgrades. Equals ESF Total Rev 3 $57,247,300.
A13: 7. All-in including D-Line interconnection 24211 (memo) | B13: =Layers!D18+Layers!B24 -> 62040544 | C13: =B13/($B$3*1000) -> 6204.0544 | D13: =B13/($B$4*1000) -> 3102.0272 | E13: =B13/$B$7 -> 5.1244167 | F13: Adds the 2024 conceptual distribution circuit extension estimate. Not yet re-estimated; treat as indicative.
A15: Battery supply contract as share of project 21334 approval level | B15: =B7/B12 -> 0.21148244
A16: Everything that is not the battery contract ($) | B16: =B12-B7 -> 45140694
A17: Interconnection-driven cost, loaded: Layer D + Layer F ($) | B17: =Layers!D8+Layers!D10 -> 13735505
A18: Interconnection-driven cost incl. D-Line memo ($) | B18: =B17+Layers!B24 -> 18528505

Sheet Timeline
A1: Cost and funding history, 2021 - 2026
A3: Date | B3: Event | C3: Value ($) | D3: Type | E3: Basis / source | F3: $/kWh at 20 MWh
A4: 2021-06 | B4: Initial Funding Request (IFR) | C4: 200000 | D4: funding | E4: IFR approved 6/11/2021; 15 MW/20 MWh concept; ISD Q3 2025 | F4: =C4/('Unit Costs'!$B$4*1000) -> 10
A5: 2023-05 | B5: IFR Rev 1 | C5: 500000 | D5: funding | E5: Cumulative initial funding $300K + $200K | F5: =C5/('Unit Costs'!$B$4*1000) -> 25
A6: 2023-07 | B6: Vendor indicative pricing, 5 bidders (Site Two, 10 MW/20 MWh) | C6: 18222342 | D6: vendor | E6: Company 3 turnkey indicative price; range $9.59M-$18.22M across bidders | F6: =C6/('Unit Costs'!$B$4*1000) -> 911.1171
A7: 2023-12 | B7: E-23-373 conceptual estimate | C7: 43926100 | D7: estimate | E7: Conceptual -25/+50%; ISD 4/23/2027; 2023 dollars escalated | F7: =C7/('Unit Costs'!$B$4*1000) -> 2196.305
A8: 2024-02 | B8: SSF preferred alternative (BESS + D-Line) | C8: 49200000 | D8: estimate | E8: $44.379M station + $4.793M distribution; SDC 2/15/2024 | F8: =C8/('Unit Costs'!$B$4*1000) -> 2460
A9: 2024-07 | B9: Partial Funding Rev 1 | C9: 4009000 | D9: funding | E9: EPAC 7/10/2024 | F9: =C9/('Unit Costs'!$B$4*1000) -> 200.45
A10: 2026-02 | B10: Partial Funding Rev 2 | C10: 5767000 | D10: funding | E10: PowerPlan 2/18/2026; FF estimate still $43.926M | F10: =C10/('Unit Costs'!$B$4*1000) -> 288.35
A11: 2026-03 | B11: Nomad cover agreement executed | C11: 12106850 | D11: vendor | E11: Fixed price, 12 Voyager units, 10-yr warranty; SOV dated 12/8/2025 | F11: =C11/('Unit Costs'!$B$4*1000) -> 605.3425
A12: 2026-06 | B12: Partial Funding Rev 3 | C12: 8914000 | D12: funding | E12: EPAC 6/25/2026; FF estimate still $43.926M; ISD 12/28/2028 | F12: =C12/('Unit Costs'!$B$4*1000) -> 445.7
A13: 2026-08 | B13: Sta 360 + 496 estimate Rev 0 | C13: 47201100 | D13: estimate | E13: ESF 8/26/2026; battery line carried at ~$6M | F13: =C13/('Unit Costs'!$B$4*1000) -> 2360.055
A14: 2026-09-01 | B14: Estimate Rev 1 | C14: 51867100 | D14: estimate | E14: Battery material increased per project team | F14: =C14/('Unit Costs'!$B$4*1000) -> 2593.355
A15: 2026-09-10 | B15: Estimate Rev 2 | C15: 63640300 | D15: estimate | E15: Battery line reset to cover agreement ($13.1M escalated) + $1.5M relays | F15: =C15/('Unit Costs'!$B$4*1000) -> 3182.015
A16: 2026-09-24 | B16: Estimate Rev 3 (current) | C16: 57247300 | D16: estimate | E16: Relays removed (-$1.5M), SSVT qty 3->1, engineering re-based to $501K + actuals | F16: =C16/('Unit Costs'!$B$4*1000) -> 2862.365
A18: In-service date drift
A19: As of | B19: Planned ISD
A20: 2021-06 | B20: Q3 2025
A21: 2023-12 | B21: Apr 2027
A22: 2024-02 | B22: Sep 2027
A23: 2026-01 | B23: Aug 2028
A24: 2026-06 | B24: Dec 2028

Sheet Sept 2026 Walk
A1: September 2026 estimate revision walk (Project 21334 approval level)
A3: Step | B3: Date | C3: Approval level ($) | D3: Change ($) | E3: Driver (from ESF clarifications and 9/1-9/23/2026 email record)
A4: Rev 0 | B4: 2026-08-26 | C4: 47201100 | D4: 0 | E4: Sta 360 built up from E-23-373 quantities and 7/28/2023 indicative pricing; battery material carried at about $6M (PM: 'change the battery cost (line 71) from 6 to 12.1M').
A5: Rev 1 | B5: 2026-09-01 | C5: 51867100 | D5: =C5-C4 -> 4666000 | E5: Per project team, increase battery material cost.
A6: Rev 2 | B6: 2026-09-10 | C6: 63640300 | D6: =C6-C5 -> 11773200 | E6: Battery line reset to Nomad cover agreement and escalated to $13,119,867; $1,545,014 'Relays, P&C systems for batteries' carried from 2023 Company 1 pricing; 3 SSVTs; engineering hours from E-23-373; $609K LNTP actuals shown separately.
A7: Rev 3 | B7: 2026-09-24 | C7: 57247300 | D7: =C7-C6 -> -6393000 | E7: Relays deleted (-$1.5M, duplicated in $300K/breaker Siemens price per P&C Engineering 9/22); SSVT quantity 3 to 1; engineering re-based to $501K to-go plus actuals (9/18); actuals updated to 9/23 ($5.52M); battery line = contract less $1,213,043 paid, escalated.
A9: Reference: full-funding placeholder carried in PF Rev 2 and Rev 3 PAFs | C9: 43926100
A10: Rev 3 vs. full-funding placeholder | C10: =C7-C9 -> 13321200 | D10: =C10/C9 -> 0.30326389

Sheet 2023 Indicative
A1: July 28, 2023 indicative pricing - Site Two (Hyde Park, 10 MW / 20 MWh), five bidders
A3: Bidder | B3: Total indicative price ($) | C3: $/kWh | D3: Notes on scope / exclusions
A4: Company 1 | B4: 11551925 | C4: =B4/('Unit Costs'!$B$4*1000) -> 577.59625 | D4: 8 Hithium containers, 4 SMA 3950 PCS skids, switchgear $707K; excludes sound mitigation; prevailing wage and IRA compliance; 5-yr warranty; interconnection by Eversource.
A5: Company 2 (Opt 1) | B5: 10532000 | C5: =B5/('Unit Costs'!$B$4*1000) -> 526.6 | D5: Assumes connection to substation bus (no switchgear); augmentation required year 7; no LTSA/extended warranty; 'Eversource would be responsible for interconnection cost'.
A6: Company 2 (Opt 2) | B6: 9586600 | C6: =B6/('Unit Costs'!$B$4*1000) -> 479.33 | D6: As Option 1 with lower-cost enclosure option.
A7: Company 3 | B7: 18222342 | C7: =B7/('Unit Costs'!$B$4*1000) -> 911.1171 | D7: Basis of the E-23-373 estimate. Battery enclosure $10.58M, PCS $0.83M, step-up transformers $0.63M, sound mitigation $0.47M, turnkey civil/installation $4.56M, spares/transport $0.59M.
A8: Company 4 | B8: 11470000 | C8: =B8/('Unit Costs'!$B$4*1000) -> 573.5 | D8: 'Complete scope' line items; no step-up transformer; no builders risk; local permits only; no below-grade risk; non-union labor.
A9: Company 5 | B9: 13915000 | C9: =B9/('Unit Costs'!$B$4*1000) -> 695.75 | D9: Highest engineering/PM line ($3.15M) and installation $2.05M.
A11: Low | B11: =MIN(B4:B9) -> 9586600
A12: High | B12: =MAX(B4:B9) -> 18222342
A13: Median | B13: =MEDIAN(B4:B9) -> 11510962
A15: Every bidder listed interconnection, permitting beyond local, below-grade risk, sound walls, spares or long-term service as excluded or 'Eversource responsibility'. Source: BESS_Indicative_Pricing.xlsx (attachment to 9/9/2026 email).

Sheet Benchmarks
A1: Published industry benchmarks (filled from research log; see whitepaper references)
A3: Source | B3: Year | C3: Metric | D3: Value | E3: Units | F3: Duration | G3: Dollar year | H3: What is included | I3: Confidence | J3: URL
A4: BloombergNEF battery pack price survey | B4: 2025 | C4: Pack price, stationary storage segment | D4: 70 | E4: $/kWh | F4: n/a | G4: 2025 real | H4: Cells and pack hardware only, ex-works. No PCS, enclosure, BOS, installation or interconnection. | I4: Medium | J4: https://about.bnef.com/insights/clean-transport/lithium-ion-battery-pack-prices-fall-to-108-per-kilowatt-hour-despite-rising-metal-prices-bloombergnef/
A5: BloombergNEF battery pack price survey | B5: 2025 | C5: Pack price, all-segment volume-weighted average | D5: 108 | E5: $/kWh | F5: n/a | G5: 2025 real | H5: Cells and pack hardware only. | I5: Medium | J5: https://about.bnef.com/insights/clean-transport/lithium-ion-battery-pack-prices-fall-to-108-per-kilowatt-hour-despite-rising-metal-prices-bloombergnef/
A6: Anza Renewables pricing insights | B6: 2026 | C6: Distribution-scale AC system price, delivered incl. tariffs, Q1 2026 | D6: 203 | E6: $/kWh | F6: distribution-scale | G6: 2026 nominal | H6: Equipment delivered (DC blocks + PCS). No EPC, civil, station or interconnection. | I6: Medium | J6: https://www.anzarenewables.com/energy-storage-pricing-insights/
A7: BloombergNEF Energy Storage System Cost Survey | B7: 2025 | C7: Turnkey system price, United States | D7: 219 | E7: $/kWh | F7: 4-h reference | G7: 2025 | H7: Racks/DC blocks, PCS, BOS, EMS, integration, installation and commissioning. Excludes grid connection, land, development and owner's costs (scope wording from prior-year summaries; verify in 2025 methodology). | I7: Medium | J7: https://www.bnef.com/insights/38229
A8: BloombergNEF Energy Storage System Cost Survey | B8: 2024 | C8: Turnkey system price, United States | D8: 236 | E8: $/kWh | F8: 4-h reference | G8: 2024 | H8: As above. | I8: Medium | J8: https://www.bnef.com/insights/35543
A9: BloombergNEF Energy Storage System Cost Survey | B9: 2023 | C9: Turnkey system price, global average (range $135-580) | D9: 263 | E9: $/kWh | F9: 4-h reference | G9: 2023 | H9: As above. | I9: Medium | J9: https://www.bnef.com/insights/33081
A10: NREL, Cole et al., Cost Projections for Utility-Scale Battery Storage: 2025 Update (NREL/TP-6A40-93281) | B10: 2025 | C10: Total installed cost, base year 2024, bottom-up model | D10: 334 | E10: $/kWh | F10: 4-h, 60 MW | G10: 2024 (verify) | H10: Pack, PCS, structural and electrical BOS, installation labor, EPC overhead, developer overhead, sales tax, permitting and an interconnection allowance, contingency, profit. Developer perspective; no utility indirects or AFUDC. | I10: High | J10: https://docs.nrel.gov/docs/fy25osti/93281.pdf
A11: EIA / Sargent & Lundy, Capital Cost and Performance Characteristics (AEO2025) | B11: 2024 | C11: Overnight capital cost, 150 MW / 600 MWh | D11: 436 | E11: $/kWh | F11: 4-h, 150 MW | G11: 2023 | H11: EPC plus owner's costs (development, land, permitting, owner's engineering, spares, contingency). Overnight: excludes AFUDC. Interconnection limited to a tie to an assumed nearby substation. $1,744/kW. | I11: High | J11: https://www.eia.gov/analysis/studies/powerplants/capitalcost/pdf/capital_cost_AEO2025.pdf
A12: LBNL, Utility-Scale Solar 2025 edition | B12: 2025 | C12: Empirical all-in battery capex, hybrid PV+storage plants installed 2024 | D12: 458 | E12: $/kWh | F12: avg 3.3-h | G12: 2024 | H12: EIA-860 reported capitalized cost, battery share of hybrid plants. | I12: High | J12: https://emp.lbl.gov/sites/default/files/2025-10/Utility%20Scale%20Solar%202025%20Edition%20Slides.pdf
A13: EIA Form 860, construction cost of generators installed in 2023 | B13: 2023 | C13: Capacity-weighted average construction cost, battery storage (6,841 MW, $9.3B) | D13: 1361 | E13: $/kW | F13: mixed (not stated) | G13: 2023 nominal | H13: Respondent-reported total capitalized construction cost. | I13: High | J13: https://www.eia.gov/electricity/generatorcosts
A14: Wood Mackenzie / ACP, US Energy Storage Monitor | B14: 2026 | C14: Utility-scale system price, Q2 2026 | D14: 916 | E14: $/kW | F14: 4-h implied | G14: 2026 | H14: Turnkey system incl. EPC; interconnection excluded (verify). | I14: Medium | J14: https://cleanpower.org/resources/u-s-energy-storage-monitor/
A15: LBNL, Interconnection cost analysis in ISO-NE (Kemp et al.) | B15: 2023 | C15: Average interconnection cost, storage requests 2018-21 | D15: 230 | E15: $/kW | F15: n/a | G15: nominal | H15: Point of interconnection plus network upgrades from ISO studies. Equals $115/kWh for a 10 MW / 20 MWh system. | I15: High | J15: https://eta-publications.lbl.gov/sites/default/files/iso-ne_interconnection_costs_vfinal.pdf
... A21: Eversource Outer Cape BESS, Provincetown (D.P.U. 17-05) | B21: 2022 | C21: Final cost $49M, 24.9 MW / 38 MWh, in service 2022 | D21: 1289 | E21: $/kWh | F21: 1.5-h, 24.9 MW | G21: 2019-22 nominal | H21: Full utility capital: batteries, PCS, site civil, microgrid islanding controls, interconnection, overheads. $1,968/kW. | I21: High | J21: https://www.utilitydive.com/news/eversource-advances-cape-cod-battery-project-defers-13-mile-distribution-l/552171/
A23: Hyde Park boundaries for comparison ($/kWh, from Unit Costs tab)
A24: Nomad equipment only (12 units, PCS, BMS, fire) | D24: =10638000/('Unit Costs'!$B$4*1000) -> 531.9 | E24: $/kWh
A25: Vendor contract | D25: ='Unit Costs'!D7 -> 605.3425 | E25: $/kWh
A26: Battery installed (A+B+C) | D26: ='Unit Costs'!D9 -> 832.86259 | E26: $/kWh
A27: Station complete, direct | D27: ='Unit Costs'!D10 -> 1483.2647 | E27: $/kWh
A28: Station 360 approval level | D28: ='Unit Costs'!D11 -> 2499.7191 | E28: $/kWh
A29: Project 21334 approval level | D29: ='Unit Costs'!D12 -> 2862.3772 | E29: $/kWh
A30: All-in incl. D-Line memo | D30: ='Unit Costs'!D13 -> 3102.0272 | E30: $/kWh
A32: Retrieved 29 Sep 2026 from search-index excerpts of the cited pages; direct PDF access was blocked in the research environment. Figures tagged High appear in the primary source text; Medium are reported by a reputable secondary source quoting the primary. Verify against the PDFs before external use.
A34: ISO interconnection cost references (LBNL series; ISO-NE Transitional Cluster Study interim, Jun 2026)
A35: LBNL ISO-NE interconnection brief | B35: 2023 | C35: Storage median, studies 2018-21 | D35: 148 | E35: $/kW | F35: n/a | G35: real (2022$ likely) | H35: POI + network upgrades from ISO studies; all-status storage mean ~ $230/kW | I35: High | J35: https://emp.lbl.gov/publications/interconnection-cost-analysis-iso-new
A36: ISO-NE Transitional Cluster Study interim | B36: 2026 | C36: Average interconnection cost, 23 transmission-connected projects (~$3.2B / 4.8 GW) | D36: 664 | E36: $/kW | F36: n/a | G36: 2026 nominal | H36: System network upgrades ~ $2.5B; WCMA > $1,000/kW, SEMA ~ $177/kW; 21 of 26 requests are BESS | I36: High (totals) / Medium (zonal) | J36: https://www.mass.gov/doc/letter-to-iso-ne-on-transitional-cluster-study-interim-results-june-25-2026/download
A37: LBNL NYISO interconnection brief | B37: 2023 | C37: Storage, 1-50 MW requests (vs $32/kW above 250 MW) | D37: 76 | E37: $/kW | F37: n/a | G37: real | H37: Only ISO-level storage cost by size | I37: High | J37: https://emp.lbl.gov/publications/interconnection-cost-analysis-nyiso
A38: LBNL PJM interconnection brief | B38: 2023 | C38: Storage mean, all statuses | D38: 335 | E38: $/kW | F38: n/a | G38: real | H38: Median $63/kW; complete storage ~ $4/kW | I38: High | J38: https://emp.lbl.gov/publications/interconnection-cost-analysis-pjm
A39: LBNL MISO interconnection brief | B39: 2022 | C39: Storage potential cost, 2018-21 | D39: 248 | E39: $/kW | F39: n/a | G39: real | I39: High | J39: https://emp.lbl.gov/publications/generator-interconnection-cost
A40: NYSERDA State of Storage | B40: 2025 | C40: Bulk (>5 MW) average installed cost | D40: 524 | E40: $/kWh | F40: n/a | G40: 2025 nominal | H40: Retail front-of-meter standalone $666/kWh | I40: High | J40: https://www.nyserda.ny.gov/
A41: Modo Energy global capex survey | B41: 2026 | C41: Median 2-h system capex (4-h: $201/kWh) | D41: 325 | E41: $/kWh | F41: 2-h | G41: 2026 nominal | H41: Doubling duration cuts ~38%/MWh | I41: Medium | J41: https://modoenergy.com/research/en/global-battery-capex-september-2026-research

Sheet Cost Curve
A1: Battery installed-cost curve and escalation basis (deck slides 10-11)
A2: Series plotted as published. Direct access to eia.gov, bnef.com and energy-storage.news was blocked by the research proxy; values come from search-index excerpts of those pages and carry the confidence tag of the excerpt. Verify against the primary pages before external use.
A4: A. Industry series as published ($/kWh)
A5: Year | B5: Series | C5: $/kWh | D5: Dollar basis | E5: Scope | F5: Confidence | G5: Source
A6: 2015 | B6: EIA reported all-in, utility-scale (EIA-860, nominal $/kWh) | C6: 2152 | D6: Nominal, capacity-weighted average energy-capacity cost of batteries installed in the year | E6: Respondent-reported total capitalized construction cost | F6: High | G6: https://www.eia.gov/todayinenergy/detail.php?id=45596
A7: 2017 | B7: EIA reported all-in, utility-scale (EIA-860, nominal $/kWh) | C7: 834 | D7: Nominal, capacity-weighted average energy-capacity cost of batteries installed in the year | E7: Respondent-reported total capitalized construction cost | F7: High | G7: https://www.eia.gov/todayinenergy/detail.php?id=45596
A8: 2018 | B8: EIA reported all-in, utility-scale (EIA-860, nominal $/kWh) | C8: 625 | D8: Nominal, capacity-weighted average energy-capacity cost of batteries installed in the year | E8: Respondent-reported total capitalized construction cost | F8: High | G8: https://www.eia.gov/todayinenergy/detail.php?id=45596
A9: 2022 | B9: BNEF turnkey system, global avg, 4-h ($/kWh, real survey-year) | C9: 324 | D9: Real USD of the survey year | E9: Racks, PCS, BOS, EMS, integration, installation, commissioning; excludes grid connection, land, development, owner's costs | F9: Medium | G9: https://www.bnef.com/insights/30443 ; https://www.bnef.com/insights/33081 ; https://www.bnef.com/insights/35543 ; https://www.bnef.com/insights/38229
A10: 2023 | B10: BNEF turnkey system, global avg, 4-h ($/kWh, real survey-year) | C10: 263 | D10: Real USD of the survey year | E10: Racks, PCS, BOS, EMS, integration, installation, commissioning; excludes grid connection, land, development, owner's costs | F10: Medium | G10: https://www.bnef.com/insights/30443 ; https://www.bnef.com/insights/33081 ; https://www.bnef.com/insights/35543 ; https://www.bnef.com/insights/38229
A11: 2024 | B11: BNEF turnkey system, global avg, 4-h ($/kWh, real survey-year) | C11: 165 | D11: Real USD of the survey year | E11: Racks, PCS, BOS, EMS, integration, installation, commissioning; excludes grid connection, land, development, owner's costs | F11: Medium | G11: https://www.bnef.com/insights/30443 ; https://www.bnef.com/insights/33081 ; https://www.bnef.com/insights/35543 ; https://www.bnef.com/insights/38229
A12: 2025 | B12: BNEF turnkey system, global avg, 4-h ($/kWh, real survey-year) | C12: 117 | D12: Real USD of the survey year | E12: Racks, PCS, BOS, EMS, integration, installation, commissioning; excludes grid connection, land, development, owner's costs | F12: Medium | G12: https://www.bnef.com/insights/30443 ; https://www.bnef.com/insights/33081 ; https://www.bnef.com/insights/35543 ; https://www.bnef.com/insights/38229
A13: 2024 | B13: BNEF turnkey system, United States, 4-h | C13: 236 | D13: Real USD of the survey year | E13: As above | F13: Medium | G13: https://www.bnef.com/insights/38229
A14: 2025 | B14: BNEF turnkey system, United States, 4-h | C14: 219 | D14: Real USD of the survey year | E14: As above | F14: Medium | G14: https://www.bnef.com/insights/38229
A15: 2024 | B15: NREL bottom-up all-in, 4-h 60 MW (2024$), mid-case projection | C15: 334 | D15: 2024 dollars; 2028 point is a linear interpolation between the 2024 base and the 2035 mid case | E15: Pack, PCS, BOS, installation, EPC and developer overhead, sales tax, permitting and interconnection allowance, contingency, profit | F15: High (2024 and 2035 points); derived (2028) | G15: https://docs.nrel.gov/docs/fy25osti/93281.pdf
A16: 2028 | B16: NREL bottom-up all-in, 4-h 60 MW (2024$), mid-case projection | C16: 302 | D16: 2024 dollars; 2028 point is a linear interpolation between the 2024 base and the 2035 mid case | E16: Pack, PCS, BOS, installation, EPC and developer overhead, sales tax, permitting and interconnection allowance, contingency, profit | F16: High (2024 and 2035 points); derived (2028) | G16: https://docs.nrel.gov/docs/fy25osti/93281.pdf
A17: 2035 | B17: NREL bottom-up all-in, 4-h 60 MW (2024$), mid-case projection | C17: 247 | D17: 2024 dollars; 2028 point is a linear interpolation between the 2024 base and the 2035 mid case | E17: Pack, PCS, BOS, installation, EPC and developer overhead, sales tax, permitting and interconnection allowance, contingency, profit | F17: High (2024 and 2035 points); derived (2028) | G17: https://docs.nrel.gov/docs/fy25osti/93281.pdf
A19: B. Hyde Park points ($/kWh at 20,000 kWh)
A20: Year (decimal) | B20: Point | C20: $/kWh | D20: Basis
A21: 2023.5 | B21: 2023 indicative bids, low (Company 2 Opt 2 $9,586,600) | C21: 479 | D21: July 2023 indicative sheet
A22: 2023.5 | B22: 2023 indicative bids, high (Company 3 $18,222,342) | C22: 911 | D22: July 2023 indicative sheet
A23: 2026.2 | B23: Nomad equipment only ($10,638,000) | C23: =Layers!B25/20000*10638000/12106850 -> 531.9 | D23: Cover agreement SOV
A24: 2026.2 | B24: Nomad contract ($12,106,850) | C24: =Layers!B25/20000 -> 605.3425 | D24: Cover agreement Exhibit C
A25: 2026.75 | B25: Battery as carried in Rev 3, layer A (contract balance escalated + actuals) | C25: =Layers!B5/20000 -> 649.55519 | D25: Rev 3 lines 432 + 445
A26: 2026.75 | B26: Battery installed, layers A+B+C | C26: =(Layers!B5+Layers!B6+Layers!B7)/20000 -> 832.86259 | D26: Rev 3 layers A, B, C
A28: C. Adjusting a 4-h, 60-240 MWh index to 2-h, 20 MWh
A29: Input | B29: Value | C29: Note
A30: Duration factor, low | B30: 1.3 | C30: NREL cost structure: pack $/kWh x hours + BOS $/kW; 2-h vs 4-h
A31: Duration factor, high | B31: 1.5 | C31: as above
A32: Size elasticity | B32: -0.173 | C32: Appendix B regression, ln(MWh) coefficient
A33: Reference MWh | B33: 240 | C33: NREL 60 MW x 4 h
A34: Hyde Park MWh | B34: 20
A35: Size factor | B35: =(B34/B33)^B32 -> 1.5370867 | C35: (20/240)^-0.173
A36: Combined factor, low | B36: =B30*B35 -> 1.9982127
A37: Combined factor, high | B37: =B31*B35 -> 2.30563
A38: BNEF US turnkey 2025, adjusted low | B38: =219*B36 -> 437.60857 | C38: vs Nomad equipment $532
A39: BNEF US turnkey 2025, adjusted high | B39: =219*B37 -> 504.93297
A40: NREL 2024 base $334 to 2028 at 3%/yr | B40: =334*(1+B43)^4 -> 375.91994
A41: NREL 2028, adjusted low | B41: =B40*B36 -> 751.16799 | C41: vs Hyde Park installed $833
A42: NREL 2028, adjusted high | B42: =B40*B37 -> 866.7323
A43: Escalation rate | B43: 0.03 | C43: ESF template, approx.
A45: D. Escalation in Rev 3 (ESF Overview row 34, included in directs)
A46: Item | B46: $ | C46: $/kWh | D46: Note
A47: Escalation, Station 360 | B47: 2622100 | C47: =B47/20000 -> 131.105 | D47: ESF Sta 360 Rev 3 Overview
A48: Escalation, Station 496 | B48: 326100 | C48: =B48/20000 -> 16.305 | D48: ESF Total Rev 3 Overview
A49: Escalation, project 21334 | B49: =B47+B48 -> 2948200 | C49: =B49/20000 -> 147.41 | D49: ESF Overview shows $2,948,100 after rounding
A50: of which on the Nomad balance (fixed price) | B50: =Layers!B26 -> 1130254.6 | C50: =B50/20000 -> 56.512732 | D50: Rev 3 line 432 less contract balance
A51: of which on other scope | B51: =B49-B50 -> 1817945.4 | C51: =B51/20000 -> 90.897267
A52: Share of approval level | B52: =B49/57247300 -> 0.051499372
A53: Spend 2027-2028 (Schedule tab) | B53: 38563658 | C53: =B53/20000 -> 1928.1829 | D53: ESF Schedule tab, 2027 + 2028 columns
A54: Escalation from a 12-month slip at the template rate | B54: =B53*B43 -> 1156909.7 | C54: =B54/20000 -> 57.845487 | D54: before AFUDC, PM, indirects
A55: Non-battery material (Materials category less layer A) | B55: =16678100-Layers!B5 -> 3686996.2 | C55: =B55/20000 -> 184.34981 | D55: exposure to tariff / commodity moves above 3%
A57: E. Same comparison, same dollars ($/kWh)
A58: Boundary | B58: Nominal as carried | C58: Ex-escalation (2026$) | D58: Benchmark brought to 2028 at the template rate | E58: Note
A59: Vendor contract | B59: =Layers!B25/20000 -> 605.3425 | C59: =B59 -> 605.3425 | D59: =219*(1+B43)^3 -> 239.30721 | E59: BNEF US turnkey 2025 -> 2028
A60: Battery as carried (A) | B60: =Layers!B5/20000 -> 649.55519 | C60: =B60-C50 -> 593.04246 | D60: =334*(1+B43)^4 -> 375.91994 | E60: NREL 4-h 2024$ -> 2028
A61: Battery installed (A+B+C) | B61: =(Layers!B5+Layers!B6+Layers!B7)/20000 -> 832.86259 | C61: =B61-C50-C51*(Layers!B6+Layers!B7)/(Layers!B6+Layers!B7+Layers!B8+Layers!B9+Layers!B11+Layers!B12+Layers!B13) -> 756.36431 | D61: =B40*B36 -> 751.16799 | E61: NREL 2028 adjusted to 2-h, 10 MW (low); high = adjusted high
A62: Station complete, direct | B62: ='Unit Costs'!D10 -> 1483.2647 | C62: =B62-C47 -> 1352.1597 | D62: =436*(1+B43)^5 -> 505.4435 | E62: EIA/S&L 2023$ -> 2028
A63: Ex-escalation removes the Station 360 escalation from the direct boundaries; the B+C share is allocated pro rata to direct cost across Station 360 layers B to I and is approximate.

Sheet Public Projects
A1: Public project-level BESS costs (44 compiled; 26 used in the regression). Blue = keyed from source; $/kWh, $/kW and duration are formulas.
A3: Project | B3: Owner | C3: Owner type | D3: State | E3: ISO | F3: MW | G3: MWh | H3: COD year | I3: Cost ($) | J3: Cost basis | K3: Scope | L3: Site type | M3: Confidence | N3: Excluded (reason) | O3: Duration (h) | P3: $/kWh | Q3: $/kW | R3: Source URL | S3: Notes | T3: In reference class? ($/kWh if yes)
A4: Outer Cape (Provincetown) BESS | B4: Eversource (NSTAR Electric) | C4: IOU | D4: MA | E4: ISO-NE | F4: 25 | G4: 38 | H4: 2022 | I4: 49000000 | J4: final/actual (as reported) | K4: all-in incl. 8,000 sf building, fiber-optic control network and Provincetown loop circuitry (microgrid) | L4: existing municipal site (town transfer station), distribution-connected | M4: Medium | O4: =IF(AND(ISNUMBER(F4),ISNUMBER(G4),F4>0),G4/F4,"") -> 1.52 | P4: =IF(AND(ISNUMBER(G4),ISNUMBER(I4),G4>0),I4/(G4*1000),"") -> 1289.4737 | Q4: =IF(AND(ISNUMBER(F4),ISNUMBER(I4),F4>0),I4/(F4*1000),"") -> 1960 | R4: https://provincetownindependent.org/featured/2026/05/13/eversource-will-upgrade-exposed-poles-on-shore-road/ | S4: DPU 17-05 (2017) approved budget range $35-45M; $49M final per Provincetown Independent and capecod.com reporting; cost includes non-battery microgrid/fiber scope | T4: =IF(AND(N4="",ISNUMBER(G4),G4<=100,ISNUMBER(P4),OR(LEFT(C4,3)="IOU",C4="muni/coop",LEFT(C4,5)="other")),P4,"") -> 1289.4737
A5: Nantucket BESS | B5: National Grid (Massachusetts Electric) | C5: IOU | D5: MA | E5: ISO-NE | F5: 6 | G5: 48 | H5: 2019 | I5: 81000000 | J5: final/actual (as reported) | K5: all-in incl. new 15 MW diesel generator and power control house | L5: existing utility site (Bunker Rd), distribution/island | M5: Medium | N5: cost bundles 15 MW diesel generator and control house | O5: =IF(AND(ISNUMBER(F5),ISNUMBER(G5),F5>0),G5/F5,"") -> 8 | P5: =IF(AND(ISNUMBER(G5),ISNUMBER(I5),G5>0),I5/(G5*1000),"") -> 1687.5 | Q5: =IF(AND(ISNUMBER(F5),ISNUMBER(I5),F5>0),I5/(F5*1000),"") -> 13500 | R5: https://www.renewableenergyworld.com/energy-storage/battery/6-mw-48-mwh-battery-storage-system-unveiled-on-nantucket-island-in-massachusetts/ | S5: Tesla Powerpack 8-hour; $81M includes generator - battery-only cost not disclosed; alternative was ~$200M third submarine cable | T5: =IF(AND(N5="",ISNUMBER(G5),G5<=100,ISNUMBER(P5),OR(LEFT(C5,3)="IOU",C5="muni/coop",LEFT(C5,5)="other")),P5,"")
A6: Martha's Vineyard BESS Phase 1 (cancelled) | B6: Eversource (NSTAR Electric) | C6: IOU | D6: MA | E6: ISO-NE | F6: 4.9 | G6: 20 | H6: 2019 | I6: 15000000 | J6: estimate (DPU 18-155 filing) | K6: all-in utility capital estimate | L6: greenfield adjacent to Oak Bluffs substation | M6: Medium | O6: =IF(AND(ISNUMBER(F6),ISNUMBER(G6),F6>0),G6/F6,"") -> 4.0816327 | P6: =IF(AND(ISNUMBER(G6),ISNUMBER(I6),G6>0),I6/(G6*1000),"") -> 750 | Q6: =IF(AND(ISNUMBER(F6),ISNUMBER(I6),F6>0),I6/(F6*1000),"") -> 3061.2245 | R6: https://www.microgridknowledge.com/distributed-energy/article/11429907/eversource-pushes-ahead-with-147-mw-battery-project-on-marthas-vineyard | S6: cod_year = DPU approval year (2019); Eversource cancelled project May 2021; never built | T6: =IF(AND(N6="",ISNUMBER(G6),G6<=100,ISNUMBER(P6),OR(LEFT(C6,3)="IOU",C6="muni/coop",LEFT(C6,5)="other")),P6,"") -> 750
A7: Martha's Vineyard BESS Phase 2 (cancelled) | B7: Eversource (NSTAR Electric) | C7: IOU | D7: MA | E7: ISO-NE | F7: 9.8 | G7: 64 | H7: 2019 | I7: 28000000 | J7: estimate (DPU 18-155 filing) | K7: all-in utility capital estimate | L7: greenfield adjacent to Oak Bluffs substation | M7: Medium | O7: =IF(AND(ISNUMBER(F7),ISNUMBER(G7),F7>0),G7/F7,"") -> 6.5306122 | P7: =IF(AND(ISNUMBER(G7),ISNUMBER(I7),G7>0),I7/(G7*1000),"") -> 437.5 | Q7: =IF(AND(ISNUMBER(F7),ISNUMBER(I7),F7>0),I7/(F7*1000),"") -> 2857.1429 | R7: https://www.microgridknowledge.com/distributed-energy/article/11429907/eversource-pushes-ahead-with-147-mw-battery-project-on-marthas-vineyard | S7: cod_year = DPU approval year (2019); planned COD 2023; cancelled May 2021 | T7: =IF(AND(N7="",ISNUMBER(G7),G7<=100,ISNUMBER(P7),OR(LEFT(C7,3)="IOU",C7="muni/coop",LEFT(C7,5)="other")),P7,"") -> 437.5
A8: Sterling MLD Chocksett Road BESS | B8: Sterling Municipal Light Department | C8: muni/coop | D8: MA | E8: ISO-NE | F8: 2 | G8: 3.9 | H8: 2016 | I8: 2700000 | J8: final/actual (as reported) | K8: turnkey battery + installation (NEC Energy Solutions) | L8: existing substation | M8: Medium | O8: =IF(AND(ISNUMBER(F8),ISNUMBER(G8),F8>0),G8/F8,"") -> 1.95 | P8: =IF(AND(ISNUMBER(G8),ISNUMBER(I8),G8>0),I8/(G8*1000),"") -> 692.30769 | Q8: =IF(AND(ISNUMBER(F8),ISNUMBER(I8),F8>0),I8/(F8*1000),"") -> 1350 | R8: https://www.cesa.org/resource-library/resource/project-overview-sterling-municipal-energy-storage-project/ | S8: $1.4M MA DOER resiliency grant + $250k DOE grant; commissioned Dec 2016 | T8: =IF(AND(N8="",ISNUMBER(G8),G8<=100,ISNUMBER(P8),OR(LEFT(C8,3)="IOU",C8="muni/coop",LEFT(C8,5)="other")),P8,"") -> 692.30769
A9: Pomona (Ladentown) BESS | B9: Orange & Rockland Utilities (Con Edison) | C9: IOU | D9: NY | E9: NYISO | F9: 3 | G9: 12 | H9: 2021 | I9: 7400000 | J9: final/actual (utility press release) | K9: all-in utility-owned (developed/built by Key Capture Energy) | L9: existing substation (adjacent Ladentown substation, O&R property) | M9: High | O9: =IF(AND(ISNUMBER(F9),ISNUMBER(G9),F9>0),G9/F9,"") -> 4 | P9: =IF(AND(ISNUMBER(G9),ISNUMBER(I9),G9>0),I9/(G9*1000),"") -> 616.66667 | Q9: =IF(AND(ISNUMBER(F9),ISNUMBER(I9),F9>0),I9/(F9*1000),"") -> 2466.6667 | R9: https://www.oru.com/en/about-us/media-center/news/2021/04-20/oru-key-capture-energy-begins-operations-at-orus-first-energy-storage-facility | S9: 4-hour; first O&R storage facility | T9: =IF(AND(N9="",ISNUMBER(G9),G9<=100,ISNUMBER(P9),OR(LEFT(C9,3)="IOU",C9="muni/coop",LEFT(C9,5)="other")),P9,"") -> 616.66667
A10: Salem Smart Power Center | B10: Portland General Electric | C10: IOU | D10: OR | E10: non-ISO (WECC NW) | F10: 5 | G10: 1.25 | H10: 2013 | I10: 23000000 | J10: final/actual (demonstration total) | K10: all-in demonstration incl. building, microgrid, smart-grid controls; DOE cost-share (PNW Smart Grid Demo) | L10: greenfield industrial site (SE Salem) | M10: High | N10: 2013 demonstration incl. building and smart-grid controls | O10: =IF(AND(ISNUMBER(F10),ISNUMBER(G10),F10>0),G10/F10,"") -> 0.25 | P10: =IF(AND(ISNUMBER(G10),ISNUMBER(I10),G10>0),I10/(G10*1000),"") -> 18400 | Q10: =IF(AND(ISNUMBER(F10),ISNUMBER(I10),F10>0),I10/(F10*1000),"") -> 4600 | R10: https://investors.portlandgeneral.com/news-releases/news-release-details/portland-general-electric-opens-salem-smart-power-center-along | S10: EnerDel Li-ion 5 MW/1.25 MWh; R&D demo - not representative of commercial cost | T10: =IF(AND(N10="",ISNUMBER(G10),G10<=100,ISNUMBER(P10),OR(LEFT(C10,3)="IOU",C10="muni/coop",LEFT(C10,5)="other")),P10,"")
A11: Waena BESS (Maui) | B11: Hawaiian Electric (Maui Electric) | C11: IOU | D11: HI | E11: non-ISO (island) | F11: 40 | G11: 160 | H11: 2027 | I11: 82100000 | J11: approved budget/estimate (HPUC Dec 2023) | K11: all-in purchase and installation; EPRM cost recovery | L11: greenfield on utility land adjacent Waena switchyard | M11: High | O11: =IF(AND(ISNUMBER(F11),ISNUMBER(G11),F11>0),G11/F11,"") -> 4 | P11: =IF(AND(ISNUMBER(G11),ISNUMBER(I11),G11>0),I11/(G11*1000),"") -> 513.125 | Q11: =IF(AND(ISNUMBER(F11),ISNUMBER(I11),F11>0),I11/(F11*1000),"") -> 2052.5 | R11: https://www.sec.gov/Archives/edgar/data/0000354707/000035470726000054/he-20260630.htm | S11: Original 2020 estimate $60M; July 2025 PUC allowed recovery up to +20% over estimate for tariff-driven cost changes; $27.2M incurred as of 6/30/2026; Tesla Megapack | T11: =IF(AND(N11="",ISNUMBER(G11),G11<=100,ISNUMBER(P11),OR(LEFT(C11,3)="IOU",C11="muni/coop",LEFT(C11,5)="other")),P11,"")
A12: Arlington Microgrid | B12: Snohomish County PUD | C12: muni/coop | D12: WA | E12: non-ISO (WECC NW) | F12: 1 | G12: 1.4 | H12: 2020 | I12: 12000000 | J12: final/actual (as reported) | K12: all-in microgrid incl. 500 kW solar, Clean Energy Center building, V2G, controls | L12: greenfield at PUD Arlington office site | M12: Medium | N12: microgrid incl. solar, building, V2G | O12: =IF(AND(ISNUMBER(F12),ISNUMBER(G12),F12>0),G12/F12,"") -> 1.4 | P12: =IF(AND(ISNUMBER(G12),ISNUMBER(I12),G12>0),I12/(G12*1000),"") -> 8571.4286 | Q12: =IF(AND(ISNUMBER(F12),ISNUMBER(I12),F12>0),I12/(F12*1000),"") -> 12000 | R12: https://www.snopud.com/community-environment/our-energy-future/projects/arlington-microgrid-project/ | S12: $3.5M WA Clean Energy Fund grant; battery-only cost not separated | T12: =IF(AND(N12="",ISNUMBER(G12),G12<=100,ISNUMBER(P12),OR(LEFT(C12,3)="IOU",C12="muni/coop",LEFT(C12,5)="other")),P12,"")
A13: Reid Gardner BESS | B13: NV Energy (Berkshire Hathaway Energy) | C13: IOU | D13: NV | E13: non-ISO (WECC; EIM) | F13: 220 | G13: 440 | H13: 2023 | I13: 257000000 | J13: final/actual (as reported) | K13: all-in | L13: coal-site (retired Reid Gardner Generating Station) | M13: Medium | O13: =IF(AND(ISNUMBER(F13),ISNUMBER(G13),F13>0),G13/F13,"") -> 2 | P13: =IF(AND(ISNUMBER(G13),ISNUMBER(I13),G13>0),I13/(G13*1000),"") -> 584.09091 | Q13: =IF(AND(ISNUMBER(F13),ISNUMBER(I13),F13>0),I13/(F13*1000),"") -> 1168.1818 | R13: https://reviewjournal.com/business/energy/nv-energy-cuts-ribbon-on-257m-facility-meant-to-boost-solar-energy-3040299 | S13: Energy Vault EPC; ~40% (~$100M) of cost offset by IRA tax credits; PUCN approved 2022 | T13: =IF(AND(N13="",ISNUMBER(G13),G13<=100,ISNUMBER(P13),OR(LEFT(C13,3)="IOU",C13="muni/coop",LEFT(C13,5)="other")),P13,"")
A14: Constable (Evergreen) BESS | B14: Portland General Electric | C14: IOU | D14: OR | E14: non-ISO (WECC NW) | F14: 75 | G14: 300 | H14: 2024 | I14: 156000000 | J14: final/actual (Electric Utility Plant recorded incl. AFUDC, 10-K) | K14: rate-base capital incl. AFUDC (EPC by Mortenson) | L14: greenfield (Hillsboro) | M14: High | O14: =IF(AND(ISNUMBER(F14),ISNUMBER(G14),F14>0),G14/F14,"") -> 4 | P14: =IF(AND(ISNUMBER(G14),ISNUMBER(I14),G14>0),I14/(G14*1000),"") -> 520 | Q14: =IF(AND(ISNUMBER(F14),ISNUMBER(I14),F14>0),I14/(F14*1000),"") -> 2080 | R14: https://www.sec.gov/Archives/edgar/data/784977/000078497725000012/por-20241231.htm | S14: 4-hour; COD Dec 2024 | T14: =IF(AND(N14="",ISNUMBER(G14),G14<=100,ISNUMBER(P14),OR(LEFT(C14,3)="IOU",C14="muni/coop",LEFT(C14,5)="other")),P14,"")
A15: Seaside BESS | B15: Portland General Electric | C15: IOU | D15: OR | E15: non-ISO (WECC NW) | F15: 200 | G15: 800 | H15: 2025 | I15: 360000000 | J15: contract price (fixed-cost build-transfer agreement, excl. AFUDC) | K15: EPC/BTA turnkey excl. AFUDC | L15: greenfield (North Portland) | M15: High | O15: =IF(AND(ISNUMBER(F15),ISNUMBER(G15),F15>0),G15/F15,"") -> 4 | P15: =IF(AND(ISNUMBER(G15),ISNUMBER(I15),G15>0),I15/(G15*1000),"") -> 450 | Q15: =IF(AND(ISNUMBER(F15),ISNUMBER(I15),F15>0),I15/(F15*1000),"") -> 1800 | R15: https://www.sec.gov/Archives/edgar/data/784977/000078497725000012/por-20241231.htm | S15: Eolian BTA; OPUC Order 25-417 rate base $220M net of $125M ITC; COD July 2025 | T15: =IF(AND(N15="",ISNUMBER(G15),G15<=100,ISNUMBER(P15),OR(LEFT(C15,3)="IOU",C15="muni/coop",LEFT(C15,5)="other")),P15,"")
A16: Essex Solar + Storage | B16: Green Mountain Power | C16: IOU | D16: VT | E16: ISO-NE | F16: 2 | G16: 8 | H16: 2022 | I16: 14300000 | J16: estimate (development + interconnection) | K16: all-in incl. 4.9 MW solar (18,326 panels) and interconnection | L16: greenfield | M16: Medium | N16: bundles 4.9 MW solar | O16: =IF(AND(ISNUMBER(F16),ISNUMBER(G16),F16>0),G16/F16,"") -> 4 | P16: =IF(AND(ISNUMBER(G16),ISNUMBER(I16),G16>0),I16/(G16*1000),"") -> 1787.5 | Q16: =IF(AND(ISNUMBER(F16),ISNUMBER(I16),F16>0),I16/(F16*1000),"") -> 7150 | R16: https://vtdigger.org/2022/09/29/green-mountain-power-expands-battery-storage-to-avoid-buying-energy-from-the-grid/ | S16: Tesla Powerpack 2 MW/4-hour; cost includes solar - not separable | T16: =IF(AND(N16="",ISNUMBER(G16),G16<=100,ISNUMBER(P16),OR(LEFT(C16,3)="IOU",C16="muni/coop",LEFT(C16,5)="other")),P16,"")
A17: Northern New York (Chateaugay) BESS | B17: New York Power Authority | C17: other (state power authority) | D17: NY | E17: NYISO | F17: 20 | G17: 20 | H17: 2023 | I17: 29800000 | J17: approved budget (NYPA Trustees) | K17: all-in | L17: existing substation (adjacent NYPA Willis substation) | M17: High | O17: =IF(AND(ISNUMBER(F17),ISNUMBER(G17),F17>0),G17/F17,"") -> 1 | P17: =IF(AND(ISNUMBER(G17),ISNUMBER(I17),G17>0),I17/(G17*1000),"") -> 1490 | Q17: =IF(AND(ISNUMBER(F17),ISNUMBER(I17),F17>0),I17/(F17*1000),"") -> 1490 | R17: https://nypa.gov/news/press-releases/2023/20230825-utility | S17: 1-hour system; initial $23.8M approval + $6M added | T17: =IF(AND(N17="",ISNUMBER(G17),G17<=100,ISNUMBER(P17),OR(LEFT(C17,3)="IOU",C17="muni/coop",LEFT(C17,5)="other")),P17,"") -> 1490
A18: Ozone Park BESS | B18: Con Edison | C18: IOU | D18: NY | E18: NYISO | F18: 1.5 | G18: 12 | H18: 2019 | I18: 15000000 | J18: estimate (utility spokesman: 'about $15 million') | K18: all-in facility | L18: utility property in Ozone Park, Queens (distribution) | M18: Low | O18: =IF(AND(ISNUMBER(F18),ISNUMBER(G18),F18>0),G18/F18,"") -> 8 | P18: =IF(AND(ISNUMBER(G18),ISNUMBER(I18),G18>0),I18/(G18*1000),"") -> 1250 | Q18: =IF(AND(ISNUMBER(F18),ISNUMBER(I18),F18>0),I18/(F18*1000),"") -> 10000 | R18: https://ny1.com/nyc/queens/news/2019/05/10/con-ed-creates-battery-farm-to-address-summer-strain-on-power-grid | S18: 8-hour; some sources cite 2 MW; cost figure is an informal spokesman statement | T18: =IF(AND(N18="",ISNUMBER(G18),G18<=100,ISNUMBER(P18),OR(LEFT(C18,3)="IOU",C18="muni/coop",LEFT(C18,5)="other")),P18,"") -> 1250
A19: Hot Springs Microgrid | B19: Duke Energy Progress | C19: IOU | D19: NC | E19: non-ISO (SERC) | F19: 4.4 | H19: 2023 | I19: 14500000 | J19: final/actual (as reported) | K19: all-in microgrid incl. 2 MW(AC) solar and controls | L19: greenfield (town of Hot Springs) | M19: Medium | N19: bundles 2 MW solar; MWh not confirmed | O19: =IF(AND(ISNUMBER(F19),ISNUMBER(G19),F19>0),G19/F19,"") | P19: =IF(AND(ISNUMBER(G19),ISNUMBER(I19),G19>0),I19/(G19*1000),"") | Q19: =IF(AND(ISNUMBER(F19),ISNUMBER(I19),F19>0),I19/(F19*1000),"") -> 3295.4545 | R19: https://www.theassemblync.com/business/hot-springs-microgrid-duke-energy/ | S19: Battery cited as 4 MW/16 MWh in NCUC filings and 4.4 MW in Duke releases; MWh left blank (not confirmed in retrieved excerpts); 2017 announcement put Hot Springs + Asheville combined at ~$30M | T19: =IF(AND(N19="",ISNUMBER(G19),G19<=100,ISNUMBER(P19),OR(LEFT(C19,3)="IOU",C19="muni/coop",LEFT(C19,5)="other")),P19,"")
A20: Virginia battery pilot portfolio (Scott Solar 10+2 MW, New Kent 2 MW, Hanover/Ashland 2 MW) | B20: Dominion Energy Virginia | C20: IOU | D20: VA | E20: PJM | F20: 16 | H20: 2022 | I20: 33000000 | J20: estimate (SCC filing, 2019) | K20: all-in construction | L20: mixed: solar co-located (Scott Solar) and substation sites | M20: Medium | O20: =IF(AND(ISNUMBER(F20),ISNUMBER(G20),F20>0),G20/F20,"") | P20: =IF(AND(ISNUMBER(G20),ISNUMBER(I20),G20>0),I20/(G20*1000),"") | Q20: =IF(AND(ISNUMBER(F20),ISNUMBER(I20),F20>0),I20/(F20*1000),"") -> 2062.5 | R20: https://www.tdworld.com/distributed-energy-resources/energy-storage/article/20972946/dominion-energy-announces-battery-storage-pilot-projects | S20: Scott Solar units are 4-hour (48 MWh); MWh for 2 MW units not confirmed so total left blank; SCC approved Feb 2020; Scott Solar operational 2022 | T20: =IF(AND(N20="",ISNUMBER(G20),G20<=100,ISNUMBER(P20),OR(LEFT(C20,3)="IOU",C20="muni/coop",LEFT(C20,5)="other")),P20,"")
A21: Glacier BESS | B21: Puget Sound Energy | C21: IOU | D21: WA | E21: non-ISO (WECC NW) | F21: 2 | G21: 4.4 | H21: 2016 | I21: 11200000 | J21: final/actual (PSE $7.4M + $3.8M state grant) | K21: all-in demonstration | L21: existing substation (adjacent Glacier substation) | M21: High | O21: =IF(AND(ISNUMBER(F21),ISNUMBER(G21),F21>0),G21/F21,"") -> 2.2 | P21: =IF(AND(ISNUMBER(G21),ISNUMBER(I21),G21>0),I21/(G21*1000),"") -> 2545.4545 | Q21: =IF(AND(ISNUMBER(F21),ISNUMBER(I21),F21>0),I21/(F21*1000),"") -> 5600 | R21: https://www.pse.com/en/pages/grid-modernization/glacier-demo-project | S21: WA Dept of Commerce $3.8M Smart Grid grant; PNNL performance reports | T21: =IF(AND(N21="",ISNUMBER(G21),G21<=100,ISNUMBER(P21),OR(LEFT(C21,3)="IOU",C21="muni/coop",LEFT(C21,5)="other")),P21,"") -> 2545.4545
A22: Chugach BESS (Southcentral Power Project site) | B22: Chugach Electric Association (75%) / Matanuska Electric Association (25%) | C22: muni/coop | D22: AK | E22: non-ISO (Railbelt) | F22: 40 | G22: 80 | H22: 2024 | I22: 65000000 | J22: final/actual (as reported) | K22: all-in | L22: existing generation site (adjacent SPP plant) | M22: High | O22: =IF(AND(ISNUMBER(F22),ISNUMBER(G22),F22>0),G22/F22,"") -> 2 | P22: =IF(AND(ISNUMBER(G22),ISNUMBER(I22),G22>0),I22/(G22*1000),"") -> 812.5 | Q22: =IF(AND(ISNUMBER(F22),ISNUMBER(I22),F22>0),I22/(F22*1000),"") -> 1625 | R22: https://www.chugachelectric.com/your-cooperative/news-community/news-releases/2024/10/7/battery-energy-storage-system-officially-commissioned | S22: 24 Tesla Megapacks; ADN reported $63M in 2023, $65M at 2024 commissioning; may qualify for ITC | T22: =IF(AND(N22="",ISNUMBER(G22),G22<=100,ISNUMBER(P22),OR(LEFT(C22,3)="IOU",C22="muni/coop",LEFT(C22,5)="other")),P22,"") -> 812.5
A23: Trenton Channel Energy Center BESS | B23: DTE Electric | C23: IOU | D23: MI | E23: MISO | F23: 220 | G23: 880 | H23: 2026 | I23: 460000000 | J23: approved estimate (MPSC, 2024) | K23: all-in incl. new substation and transmission tie | L23: coal-site (retired Trenton Channel plant) | M23: Medium | O23: =IF(AND(ISNUMBER(F23),ISNUMBER(G23),F23>0),G23/F23,"") -> 4 | P23: =IF(AND(ISNUMBER(G23),ISNUMBER(I23),G23>0),I23/(G23*1000),"") -> 522.72727 | Q23: =IF(AND(ISNUMBER(F23),ISNUMBER(I23),F23>0),I23/(F23*1000),"") -> 2090.9091 | R23: https://www.energy-storage.news/us-utility-dte-starts-220mw-880mwh-bess-project-at-michigan-coal-plant-site/ | S23: Powin LFP; ~$140M IRA tax credits offset; planned COD 2026 | T23: =IF(AND(N23="",ISNUMBER(G23),G23<=100,ISNUMBER(P23),OR(LEFT(C23,3)="IOU",C23="muni/coop",LEFT(C23,5)="other")),P23,"")
A24: Roadrunner Reserve (Phase 1) | B24: Tucson Electric Power | C24: IOU | D24: AZ | E24: non-ISO (WECC SW) | F24: 200 | G24: 800 | H24: 2025 | I24: 294000000 | J24: estimate at announcement (2023) | K24: EPC turnkey (DEPCOM Power) | L24: greenfield (SE Tucson) | M24: Medium | O24: =IF(AND(ISNUMBER(F24),ISNUMBER(G24),F24>0),G24/F24,"") -> 4 | P24: =IF(AND(ISNUMBER(G24),ISNUMBER(I24),G24>0),I24/(G24*1000),"") -> 367.5 | Q24: =IF(AND(ISNUMBER(F24),ISNUMBER(I24),F24>0),I24/(F24*1000),"") -> 1470 | R24: https://tucson.com/news/local/business/article_95df9266-623a-11ee-8f58-8bdd862facf6.html | S24: TEP later described the first 200 MW as a '$350 million investment' (tep.com) - unclear whether $350M is updated Phase 1 cost or Phase 2; both reported | T24: =IF(AND(N24="",ISNUMBER(G24),G24<=100,ISNUMBER(P24),OR(LEFT(C24,3)="IOU",C24="muni/coop",LEFT(C24,5)="other")),P24,"")
A25: Roadrunner Reserve 2 (Phase 2) | B25: Tucson Electric Power | C25: IOU | D25: AZ | E25: non-ISO (WECC SW) | F25: 200 | G25: 800 | H25: 2026 | I25: 350000000 | J25: estimate (utility statement) | K25: all-in | L25: existing site expansion (adjacent Phase 1) | M25: Medium | O25: =IF(AND(ISNUMBER(F25),ISNUMBER(G25),F25>0),G25/F25,"") -> 4 | P25: =IF(AND(ISNUMBER(G25),ISNUMBER(I25),G25>0),I25/(G25*1000),"") -> 437.5 | Q25: =IF(AND(ISNUMBER(F25),ISNUMBER(I25),F25>0),I25/(F25*1000),"") -> 1750 | R25: https://www.tep.com/roadrunner/ | S25: Online June 2026 per TEP; combined 400 MW / 1,600 MWh | T25: =IF(AND(N25="",ISNUMBER(G25),G25<=100,ISNUMBER(P25),OR(LEFT(C25,3)="IOU",C25="muni/coop",LEFT(C25,5)="other")),P25,"")
A26: Minnesota utility-owned distribution battery program (200 MW) | B26: Xcel Energy (Northern States Power-MN) | C26: IOU | D26: MN | E26: MISO | F26: 200 | H26: 2026 | I26: 430000000 | J26: approved program budget (MPUC, 2026) | K26: rate-base program capital (multiple distribution sites) | L26: distribution substations (various) | M26: Medium | N26: program budget, MWh not stated | O26: =IF(AND(ISNUMBER(F26),ISNUMBER(G26),F26>0),G26/F26,"") | P26: =IF(AND(ISNUMBER(G26),ISNUMBER(I26),G26>0),I26/(G26*1000),"") | Q26: =IF(AND(ISNUMBER(F26),ISNUMBER(I26),F26>0),I26/(F26*1000),"") -> 2150 | R26: https://www.utilitydive.com/news/minnesota-approves-xcels-controversial-utility-owned-virtual-power-plant/816673/ | S26: Programmatic, not a single project; PUC approved 200 MW with interim assessment at 50 MW; duration not confirmed in retrieved excerpt | T26: =IF(AND(N26="",ISNUMBER(G26),G26<=100,ISNUMBER(P26),OR(LEFT(C26,3)="IOU",C26="muni/coop",LEFT(C26,5)="other")),P26,"")
A27: Harding Street BESS | B27: Indianapolis Power & Light (AES Indiana) | C27: IOU | D27: IN | E27: MISO | F27: 20 | G27: 20 | H27: 2016 | I27: 25000000 | J27: estimate at announcement (2015) | K27: all-in | L27: existing generation site (Harding Street station) | M27: Medium | O27: =IF(AND(ISNUMBER(F27),ISNUMBER(G27),F27>0),G27/F27,"") -> 1 | P27: =IF(AND(ISNUMBER(G27),ISNUMBER(I27),G27>0),I27/(G27*1000),"") -> 1250 | Q27: =IF(AND(ISNUMBER(F27),ISNUMBER(I27),F27>0),I27/(F27*1000),"") -> 1250 | R27: https://www.utilitydive.com/news/indianapolis-power-light-to-invest-25m-in-storage-facility/399502/ | S27: First MISO grid battery; primary frequency response; placed in rate base | T27: =IF(AND(N27="",ISNUMBER(G27),G27<=100,ISNUMBER(P27),OR(LEFT(C27,3)="IOU",C27="muni/coop",LEFT(C27,5)="other")),P27,"") -> 1250
A28: Kingsbery Community Solar + Storage | B28: Austin Energy | C28: muni/coop | D28: TX | E28: ERCOT | F28: 1.5 | G28: 3 | H28: 2016 | I28: 3000000 | J28: final/actual (as reported) | K28: all-in battery incl. install at community solar site | L28: existing substation (Kingsbery) with community solar | M28: Medium | O28: =IF(AND(ISNUMBER(F28),ISNUMBER(G28),F28>0),G28/F28,"") -> 2 | P28: =IF(AND(ISNUMBER(G28),ISNUMBER(I28),G28>0),I28/(G28*1000),"") -> 1000 | Q28: =IF(AND(ISNUMBER(F28),ISNUMBER(I28),F28>0),I28/(F28*1000),"") -> 2000 | R28: https://www.statesman.com/story/news/2016/09/04/austin-energy-poised-to-test-its-first-energy-storage-system/9995279007/ | S28: $1M TCEQ grant; Tesla battery (Younicos integrator) | T28: =IF(AND(N28="",ISNUMBER(G28),G28<=100,ISNUMBER(P28),OR(LEFT(C28,3)="IOU",C28="muni/coop",LEFT(C28,5)="other")),P28,"") -> 1000
A29: Nova Scotia BESS portfolio (Bridgewater, Waverley, White Rock; 3 x 50 MW) [CANADA] | B29: Nova Scotia Power (Emera) with Wskijnu'k Mtmo'taqnuow Agency | C29: IOU | D29: NS (Canada) | E29: non-ISO (NS Power) | F29: 150 | G29: 600 | H29: 2026 | I29: 258000000 | J29: approved budget (NSUARB) incl. AFUDC | K29: rate-base capital incl. AFUDC | L29: greenfield (3 sites) | M29: High | O29: =IF(AND(ISNUMBER(F29),ISNUMBER(G29),F29>0),G29/F29,"") -> 4 | P29: =IF(AND(ISNUMBER(G29),ISNUMBER(I29),G29>0),I29/(G29*1000),"") -> 430 | Q29: =IF(AND(ISNUMBER(F29),ISNUMBER(I29),F29>0),I29/(F29*1000),"") -> 1720 | R29: https://www.cbc.ca/news/canada/nova-scotia/nsp-battery-storage-system-approved-1.7235197 | S29: Reported C$354M incl AFUDC; converted at ~0.73 USD/CAD (approximate); C$109M NRCan grant + C$138.2M CIB loan; 4-hour | T29: =IF(AND(N29="",ISNUMBER(G29),G29<=100,ISNUMBER(P29),OR(LEFT(C29,3)="IOU",C29="muni/coop",LEFT(C29,5)="other")),P29,"")
A30: Guam ESS (Agana 24 MW/6 MWh + Talofofo 16 MW/16 MWh) | B30: Guam Power Authority | C30: muni/coop | D30: GU | E30: non-ISO (island) | F30: 40 | G30: 22 | I30: 43000000 | J30: contract price (turnkey, 2017) | K30: EPC turnkey (LG CNS) | L30: existing substations | M30: Medium | O30: =IF(AND(ISNUMBER(F30),ISNUMBER(G30),F30>0),G30/F30,"") -> 0.55 | P30: =IF(AND(ISNUMBER(G30),ISNUMBER(I30),G30>0),I30/(G30*1000),"") -> 1954.5455 | Q30: =IF(AND(ISNUMBER(F30),ISNUMBER(I30),F30>0),I30/(F30*1000),"") -> 1075 | R30: https://www.utilitydive.com/news/lg-subsidiary-will-install-40-mw-of-batteries-on-guam/444490/ | S30: Two systems under one $43M contract; 12-month delivery from 2017; reported operating by 2021; COD year not confirmed in excerpts | T30: =IF(AND(N30="",ISNUMBER(G30),G30<=100,ISNUMBER(P30),OR(LEFT(C30,3)="IOU",C30="muni/coop",LEFT(C30,5)="other")),P30,"") -> 1954.5455
A31: Fairhaven BESS | B31: Baltimore Gas & Electric (Exelon) | C31: IOU | D31: MD | E31: PJM | F31: 2.5 | G31: 9.74 | H31: 2023 | I31: 16161336 | J31: final/actual (reported to MD PSC) | K31: all-in utility-owned | L31: existing substation (Fairhaven) | M31: High | O31: =IF(AND(ISNUMBER(F31),ISNUMBER(G31),F31>0),G31/F31,"") -> 3.896 | P31: =IF(AND(ISNUMBER(G31),ISNUMBER(I31),G31>0),I31/(G31*1000),"") -> 1659.2747 | Q31: =IF(AND(ISNUMBER(F31),ISNUMBER(I31),F31>0),I31/(F31*1000),"") -> 6464.5344 | R31: https://psc.maryland.gov/wp-content/uploads/Energy-Storage-Pilot-Program-Interim-Report.pdf | S31: Initial estimate $9,841,000; actual $16,161,336; MWh cited as 7.1 (proposal) and 9.74 (interim report); PJM frequency regulation + winter peak | T31: =IF(AND(N31="",ISNUMBER(G31),G31<=100,ISNUMBER(P31),OR(LEFT(C31,3)="IOU",C31="muni/coop",LEFT(C31,5)="other")),P31,"") -> 1659.2747
A32: Regina BESS [CANADA] | B32: SaskPower | C32: other (crown utility) | D32: SK (Canada) | E32: non-ISO (SaskPower) | F32: 20 | H32: 2024 | I32: 25000000 | J32: final/actual (as reported) | K32: all-in | L32: greenfield (Regina) | M32: High | O32: =IF(AND(ISNUMBER(F32),ISNUMBER(G32),F32>0),G32/F32,"") | P32: =IF(AND(ISNUMBER(G32),ISNUMBER(I32),G32>0),I32/(G32*1000),"") | Q32: =IF(AND(ISNUMBER(F32),ISNUMBER(I32),F32>0),I32/(F32*1000),"") -> 1250 | R32: https://www.cbc.ca/news/canada/saskatchewan/saskpower-battery-energy-storage-1.7253756 | S32: Reported C$34M (initial estimate C$26M); converted at ~0.74 USD/CAD; federal contribution C$13.1M; MWh not confirmed in retrieved excerpt | T32: =IF(AND(N32="",ISNUMBER(G32),G32<=100,ISNUMBER(P32),OR(LEFT(C32,3)="IOU",C32="muni/coop",LEFT(C32,5)="other")),P32,"")
A33: Stafford Hill Solar + Storage (Rutland) | B33: Green Mountain Power | C33: IOU | D33: VT | E33: ISO-NE | F33: 4 | G33: 3.4 | H33: 2015 | I33: 4200000 | J33: final/actual (storage component) | K33: battery + inverters (storage share of $10M project) | L33: greenfield (capped landfill) with 2.5 MW solar | M33: Medium | O33: =IF(AND(ISNUMBER(F33),ISNUMBER(G33),F33>0),G33/F33,"") -> 0.85 | P33: =IF(AND(ISNUMBER(G33),ISNUMBER(I33),G33>0),I33/(G33*1000),"") -> 1235.2941 | Q33: =IF(AND(ISNUMBER(F33),ISNUMBER(I33),F33>0),I33/(F33*1000),"") -> 1050 | R33: https://www.cleanegroup.org/initiatives/technical-assistance-fund/featured-installations/stafford-hill/ | S33: Mixed chemistry: 2 MW/1 MWh Li-ion + 2 MW/2.4 MWh advanced lead-acid; solar portion ~$5.77M | T33: =IF(AND(N33="",ISNUMBER(G33),G33<=100,ISNUMBER(P33),OR(LEFT(C33,3)="IOU",C33="muni/coop",LEFT(C33,5)="other")),P33,"") -> 1235.2941
A34: Westside Canal BESS Phase 2a | B34: San Diego Gas & Electric (Sempra) | C34: IOU | D34: CA | E34: CAISO | F34: 119 | H34: 2024 | I34: 267900000 | J34: approved estimate (CPUC) | K34: all-in utility-owned | L34: existing site (adjacent Westside Canal Phase 1, Imperial Valley) | M34: High | O34: =IF(AND(ISNUMBER(F34),ISNUMBER(G34),F34>0),G34/F34,"") | P34: =IF(AND(ISNUMBER(G34),ISNUMBER(I34),G34>0),I34/(G34*1000),"") | Q34: =IF(AND(ISNUMBER(F34),ISNUMBER(I34),F34>0),I34/(F34*1000),"") -> 2251.2605 | R34: https://www.sempra.com/newsroom/press-releases/sdge-expands-energy-storage-capabilities-enhance-grid-resiliency-and | S34: COD Dec 2024; duration/MWh not confirmed in retrieved excerpt (SDG&E portfolio is predominantly 4-hour) | T34: =IF(AND(N34="",ISNUMBER(G34),G34<=100,ISNUMBER(P34),OR(LEFT(C34,3)="IOU",C34="muni/coop",LEFT(C34,5)="other")),P34,"")
A35: Westside Canal BESS Phase 2b (expansion) | B35: San Diego Gas & Electric (Sempra) | C35: IOU | D35: CA | E35: CAISO | F35: 100 | H35: 2025 | I35: 224500000 | J35: approved estimate (CPUC, Mar 2025) | K35: all-in utility-owned | L35: existing site expansion (Imperial Valley) | M35: High | O35: =IF(AND(ISNUMBER(F35),ISNUMBER(G35),F35>0),G35/F35,"") | P35: =IF(AND(ISNUMBER(G35),ISNUMBER(I35),G35>0),I35/(G35*1000),"") | Q35: =IF(AND(ISNUMBER(F35),ISNUMBER(I35),F35>0),I35/(F35*1000),"") -> 2245 | R35: https://www.sempra.com/newsroom/press-releases/sdge-expands-energy-storage-capabilities-enhance-grid-resiliency-and | S35: Adds 100 MW to existing 131 MW facility; projected fully operational June 2025; MWh not confirmed | T35: =IF(AND(N35="",ISNUMBER(G35),G35<=100,ISNUMBER(P35),OR(LEFT(C35,3)="IOU",C35="muni/coop",LEFT(C35,5)="other")),P35,"")
A36: Smarter Network Storage (Leighton Buzzard) [UK] | B36: UK Power Networks | C36: IOU (regulated DNO) | D36: Bedfordshire (UK) | E36: GB (National Grid ESO) | F36: 6 | G36: 10 | H36: 2014 | I36: 29000000 | J36: final (project budget) | K36: all-in demonstration incl. trials/R&D (Low Carbon Networks Fund) | L36: existing primary substation | M36: High | N36: R&D demonstration incl. trials | O36: =IF(AND(ISNUMBER(F36),ISNUMBER(G36),F36>0),G36/F36,"") -> 1.6666667 | P36: =IF(AND(ISNUMBER(G36),ISNUMBER(I36),G36>0),I36/(G36*1000),"") -> 2900 | Q36: =IF(AND(ISNUMBER(F36),ISNUMBER(I36),F36>0),I36/(F36*1000),"") -> 4833.3333 | R36: https://innovation.ukpowernetworks.co.uk/projects/smarter-network-storage-sns | S36: Reported GBP 18.7M; converted at ~1.55 USD/GBP (2014); Samsung SDI/S&C/Younicos | T36: =IF(AND(N36="",ISNUMBER(G36),G36<=100,ISNUMBER(P36),OR(LEFT(C36,3)="IOU",C36="muni/coop",LEFT(C36,5)="other")),P36,"")
A37: Dalrymple ESCRI BESS [AUSTRALIA] | B37: ElectraNet (transmission network service provider) | C37: IOU (regulated TNSP) | D37: SA (Australia) | E37: NEM | F37: 30 | G37: 8 | H37: 2018 | I37: 22200000 | J37: final/actual (as reported) | K37: all-in | L37: existing substation (Dalrymple) | M37: High | O37: =IF(AND(ISNUMBER(F37),ISNUMBER(G37),F37>0),G37/F37,"") -> 0.26666667 | P37: =IF(AND(ISNUMBER(G37),ISNUMBER(I37),G37>0),I37/(G37*1000),"") -> 2775 | Q37: =IF(AND(ISNUMBER(F37),ISNUMBER(I37),F37>0),I37/(F37*1000),"") -> 740 | R37: https://arena.gov.au/news/grid-scale-escri-battery-charges-up-in-south-australia/ | S37: Reported A$30M; converted at ~0.74 USD/AUD (2018); A$12M ARENA grant later repaid; operated by AGL under lease | T37: =IF(AND(N37="",ISNUMBER(G37),G37<=100,ISNUMBER(P37),OR(LEFT(C37,3)="IOU",C37="muni/coop",LEFT(C37,5)="other")),P37,"") -> 2775
A38: Oneida Energy Storage [CANADA] | B38: Northland Power / Six Nations of the Grand River / NRStor / Aecon | C38: IPP | D38: ON (Canada) | E38: IESO | F38: 250 | G38: 1000 | H38: 2025 | I38: 511000000 | J38: final/actual (reported ~C$700M vs C$800M budget) | K38: all-in | L38: greenfield (Haldimand County) | M38: High | O38: =IF(AND(ISNUMBER(F38),ISNUMBER(G38),F38>0),G38/F38,"") -> 4 | P38: =IF(AND(ISNUMBER(G38),ISNUMBER(I38),G38>0),I38/(G38*1000),"") -> 511 | Q38: =IF(AND(ISNUMBER(F38),ISNUMBER(I38),F38>0),I38/(F38*1000),"") -> 2044 | R38: https://www.northlandpower.com/en/news/press-release/northland-power-announces-commercial-operations-at-oneida-energy-storage-project-canadas-largest-bat.aspx | S38: Converted at ~0.73 USD/CAD; CIB loan; IESO capacity contract; COD May 2025 | T38: =IF(AND(N38="",ISNUMBER(G38),G38<=100,ISNUMBER(P38),OR(LEFT(C38,3)="IOU",C38="muni/coop",LEFT(C38,5)="other")),P38,"")
A39: SwRI Solar + Storage (5 MW PV + 10 MW BESS) | B39: CPS Energy | C39: muni/coop | D39: TX | E39: ERCOT | F39: 10 | G39: 10 | H39: 2019 | I39: 16300000 | J39: approved budget (CPS Board) | K39: all-in incl. 5 MW solar | L39: greenfield (SwRI land, San Antonio) | M39: Medium | N39: bundles 5 MW solar | O39: =IF(AND(ISNUMBER(F39),ISNUMBER(G39),F39>0),G39/F39,"") -> 1 | P39: =IF(AND(ISNUMBER(G39),ISNUMBER(I39),G39>0),I39/(G39*1000),"") -> 1630 | Q39: =IF(AND(ISNUMBER(F39),ISNUMBER(I39),F39>0),I39/(F39*1000),"") -> 1630 | R39: https://www.powermag.com/press-releases/cps-energy-launches-solar-energy-and-battery-storage-project/ | S39: $3M TCEQ NTIG grant; cost includes solar - not separable | T39: =IF(AND(N39="",ISNUMBER(G39),G39<=100,ISNUMBER(P39),OR(LEFT(C39,3)="IOU",C39="muni/coop",LEFT(C39,5)="other")),P39,"")
A40: SCE substation BESS portfolio (Springvale 225 MW, Hinson 200 MW, Etiwanda 112.5 MW) | B40: Southern California Edison | C40: IOU | D40: CA | E40: CAISO | F40: 537.5 | G40: 2150 | H40: 2022 | I40: 1226000000 | J40: contract price (EPCM contract, CPUC-authorized Dec 2021) | K40: EPC + maintenance (Ameresco EPCM) | L40: existing substations | M40: High | O40: =IF(AND(ISNUMBER(F40),ISNUMBER(G40),F40>0),G40/F40,"") -> 4 | P40: =IF(AND(ISNUMBER(G40),ISNUMBER(I40),G40>0),I40/(G40*1000),"") -> 570.23256 | Q40: =IF(AND(ISNUMBER(F40),ISNUMBER(I40),F40>0),I40/(F40*1000),"") -> 2280.9302 | R40: https://www.cpuc.ca.gov/news-and-updates/all-news/cpuc-approves-energy-storage-contract-for-sce | S40: 4-hour; emergency reliability procurement under 2021 Governor's proclamation; aggregate of three sites | T40: =IF(AND(N40="",ISNUMBER(G40),G40<=100,ISNUMBER(P40),OR(LEFT(C40,3)="IOU",C40="muni/coop",LEFT(C40,5)="other")),P40,"")
A41: Whitehorse Grid-Scale BESS [CANADA] | B41: Yukon Energy | C41: other (crown utility) | D41: YT (Canada) | E41: non-ISO (Yukon isolated grid) | F41: 7 | G41: 40 | I41: 23600000 | J41: estimate (2020$, +/-30%, Yukon Utilities Board application) | K41: all-in | L41: greenfield (Whitehorse) | M41: High | O41: =IF(AND(ISNUMBER(F41),ISNUMBER(G41),F41>0),G41/F41,"") -> 5.7142857 | P41: =IF(AND(ISNUMBER(G41),ISNUMBER(I41),G41>0),I41/(G41*1000),"") -> 590 | Q41: =IF(AND(ISNUMBER(F41),ISNUMBER(I41),F41>0),I41/(F41*1000),"") -> 3371.4286 | R41: https://yukonenergy.ca/energy-in-yukon/projects-facilities/battery-storage | S41: Reported C$31.7M; converted at ~0.745 USD/CAD; C$16.5M federal grant; SunGrid Solutions EPC; COD not confirmed in retrieved excerpts (planned 2023) | T41: =IF(AND(N41="",ISNUMBER(G41),G41<=100,ISNUMBER(P41),OR(LEFT(C41,3)="IOU",C41="muni/coop",LEFT(C41,5)="other")),P41,"") -> 590
A42: Rock Hill (Asheville) substation BESS | B42: Duke Energy Progress | C42: IOU | D42: NC | E42: non-ISO (SERC) | F42: 9 | H42: 2020 | I42: 15000000 | J42: estimate (upper bound: 'less than $15 million') | K42: all-in | L42: existing substation (Rock Hill, Sweeten Creek Rd) | M42: Medium | O42: =IF(AND(ISNUMBER(F42),ISNUMBER(G42),F42>0),G42/F42,"") | P42: =IF(AND(ISNUMBER(G42),ISNUMBER(I42),G42>0),I42/(G42*1000),"") | Q42: =IF(AND(ISNUMBER(F42),ISNUMBER(I42),F42>0),I42/(F42*1000),"") -> 1666.6667 | R42: https://news.duke-energy.com/releases/north-carolinas-largest-battery-system-now-operating-at-duke-energy-substation | S42: Cost is an upper bound; MWh not confirmed; 2017 announcement: Hot Springs + Asheville ~$30M combined | T42: =IF(AND(N42="",ISNUMBER(G42),G42<=100,ISNUMBER(P42),OR(LEFT(C42,3)="IOU",C42="muni/coop",LEFT(C42,5)="other")),P42,"")
A43: Morro Bay BESS (proposed, not built) | B43: Vistra | C43: IPP | D43: CA | E43: CAISO | F43: 600 | G43: 2400 | I43: 550000000 | J43: estimate ($500-600M, developer statement) | K43: all-in | L43: existing retired gas plant site (Morro Bay) | M43: Low | N43: proposed, no COD, developer statement | O43: =IF(AND(ISNUMBER(F43),ISNUMBER(G43),F43>0),G43/F43,"") -> 4 | P43: =IF(AND(ISNUMBER(G43),ISNUMBER(I43),G43>0),I43/(G43*1000),"") -> 229.16667 | Q43: =IF(AND(ISNUMBER(F43),ISNUMBER(I43),F43>0),I43/(F43*1000),"") -> 916.66667 | R43: https://esterobaynews.com/featured-stories/vistra-proposes-worlds-biggest-battery-storage-facility/ | S43: Midpoint of $500-600M range; local approval not obtained; project status uncertain/reportedly shelved; cod_year blank | T43: =IF(AND(N43="",ISNUMBER(G43),G43<=100,ISNUMBER(P43),OR(LEFT(C43,3)="IOU",C43="muni/coop",LEFT(C43,5)="other")),P43,"")
A44: Kwinana BESS Stage 1 [AUSTRALIA] | B44: Synergy (WA state-owned utility) | C44: other (state-owned utility) | D44: WA (Australia) | E44: SWIS/WEM | F44: 100 | G44: 200 | H44: 2023 | I44: 103500000 | J44: final (as reported) | K44: all-in | L44: coal-site (decommissioned Kwinana Power Station) | M44: Medium | O44: =IF(AND(ISNUMBER(F44),ISNUMBER(G44),F44>0),G44/F44,"") -> 2 | P44: =IF(AND(ISNUMBER(G44),ISNUMBER(I44),G44>0),I44/(G44*1000),"") -> 517.5 | Q44: =IF(AND(ISNUMBER(F44),ISNUMBER(I44),F44>0),I44/(F44*1000),"") -> 1035 | R44: https://www.pv-magazine-australia.com/2023/05/15/wa-plans-bigger-batteries-as-200-kwinana-system-put-to-test/ | S44: Reported A$155M (USD 103.5M as stated by source); state/federal funded | T44: =IF(AND(N44="",ISNUMBER(G44),G44<=100,ISNUMBER(P44),OR(LEFT(C44,3)="IOU",C44="muni/coop",LEFT(C44,5)="other")),P44,"")
A45: WindCharger [CANADA] | B45: TransAlta Renewables | C45: IPP | D45: AB (Canada) | E45: AESO | F45: 10 | G45: 20 | H45: 2020 | I45: 11000000 | J45: final/actual (total capital cost) | K45: all-in | L45: existing wind farm site (Summerview II) | M45: Medium | O45: =IF(AND(ISNUMBER(F45),ISNUMBER(G45),F45>0),G45/F45,"") -> 2 | P45: =IF(AND(ISNUMBER(G45),ISNUMBER(I45),G45>0),I45/(G45*1000),"") -> 550 | Q45: =IF(AND(ISNUMBER(F45),ISNUMBER(I45),F45>0),I45/(F45*1000),"") -> 1100 | R45: https://renewablesnow.com/news/transalta-renewables-10-mw-wind-powered-battery-reaches-cod-in-alberta-717754/ | S45: Reported C$14.5M (USD 11M as stated by source); ~50% ERA grant; Tesla Megapack | T45: =IF(AND(N45="",ISNUMBER(G45),G45<=100,ISNUMBER(P45),OR(LEFT(C45,3)="IOU",C45="muni/coop",LEFT(C45,5)="other")),P45,"")
A46: Weld Energy Storage (for Platte River Power Authority) | B46: Weld Energy Storage LLC (NextEra Energy Resources) | C46: IPP | D46: CO | E46: non-ISO (WECC) | G46: 400 | H46: 2026 | I46: 141000000 | J46: estimate (reported project cost) | K46: all-in | L46: greenfield (Weld County) | M46: Medium | O46: =IF(AND(ISNUMBER(F46),ISNUMBER(G46),F46>0),G46/F46,"") | P46: =IF(AND(ISNUMBER(G46),ISNUMBER(I46),G46>0),I46/(G46*1000),"") -> 352.5 | Q46: =IF(AND(ISNUMBER(F46),ISNUMBER(I46),F46>0),I46/(F46*1000),"") | R46: https://coloradobiz.com/platte-river-energy-storage-weld-county-battery-project/ | S46: IPP-owned under long-term storage agreement with Platte River; MW not confirmed in retrieved excerpt; planned COD late 2026 | T46: =IF(AND(N46="",ISNUMBER(G46),G46<=100,ISNUMBER(P46),OR(LEFT(C46,3)="IOU",C46="muni/coop",LEFT(C46,5)="other")),P46,"")
A47: Glenarm BESS (for Pasadena Water & Power) | B47: Glenarm BESS LLC (EPC Energy SPE) | C47: IPP | D47: CA | E47: CAISO | F47: 25 | G47: 100 | H47: 2027 | I47: 55300000 | J47: contract price (15-year services contract value) | K47: contract value - not a construction cost | L47: existing gas plant site (Glenarm Power Plant) | M47: Medium | N47: 15-year contract value, not capex | O47: =IF(AND(ISNUMBER(F47),ISNUMBER(G47),F47>0),G47/F47,"") -> 4 | P47: =IF(AND(ISNUMBER(G47),ISNUMBER(I47),G47>0),I47/(G47*1000),"") -> 553 | Q47: =IF(AND(ISNUMBER(F47),ISNUMBER(I47),F47>0),I47/(F47*1000),"") -> 2212 | R47: https://pasadenanow.com/main/city-committee-unanimously-approves-100-million-long-term-contracts-for-renewable-energy-battery-energy-storage | S47: $9.6M CEC DEBA grant to PWP; 4-hour; planned COD 2027; treat as contract value not capex | T47: =IF(AND(N47="",ISNUMBER(G47),G47<=100,ISNUMBER(P47),OR(LEFT(C47,3)="IOU",C47="muni/coop",LEFT(C47,5)="other")),P47,"")
A49: Reference class (utility-owned, <=100 MWh, not excluded): median $/kWh | P49: =MEDIAN(T4:T47) -> 1242.6471 | Q49: =COUNT(T4:T47) -> 16
A50: Column T flags the reference class (utility-owned, <= 100 MWh, not excluded); the median and count above are live formulas. The Statistics tab carries the Python run values as of 29 Sep 2026.

Sheet 2026$ Adjustment
A1: Dollar-year adjustment of the public comparables to 2026 (deck slides 12-13)
A2: cost_2026 = cost_nominal x [ s x I(2026)/I(y) + (1 - s) x (1 + g)^(2026 - y) ] s = battery share of the comparable, I = battery index, g = non-battery construction escalation. Blue = inputs.
A4: Battery share s | B4: 0.4
A5: Construction escalation g | B5: 0.035
A6: Index selector (1 installed, 2 pack, 3 LCOS) | B6: 1
A8: A. Battery indices as published ($/kWh; LCOS $/MWh)
A9: Year | B9: Installed all-in (EIA-860, LBNL) | C9: BNEF pack (real) | D9: Lazard LCOS midpoint | E9: Note
A10: 2015 | B10: 2152 | C10: 373 | D10: 245 | E10: published
A11: 2016 | B11: 1493 | C11: 288 | D11: 245 | E11: published
A12: 2017 | B12: 834 | C12: 214 | D12: 245 | E12: published
A13: 2018 | B13: 625 | C13: 176 | D13: 245 | E13: published
A14: 2019 | B14: 597 | C14: 156 | D14: 245 | E14: published
A15: 2020 | B15: 569 | C15: 137 | D15: 191 | E15: published
A16: 2021 | B16: 542 | C16: 132 | D16: 202 | E16: published
A17: 2022 | B17: 514 | C17: 151 | D17: 212 | E17: published
A18: 2023 | B18: 486 | C18: 139 | D18: 222 | E18: published
A19: 2024 | B19: 458 | C19: 115 | D19: 233 | E19: published
A20: 2025 | B20: 458 | C20: 108 | D20: 185 | E20: published
A21: 2026 | B21: 458 | C21: 108 | D21: 251 | E21: published
A22: Sources: EIA Today in Energy #45596 (2015-18); LBNL Utility-Scale Solar 2025 (2024); BNEF Lithium-Ion Battery Price Survey 2015-2025; Lazard LCOS v5.0, v6.0, LCOE+ 2024-2026 (unsubsidized 100 MW / 4-h range midpoints). Black values are linear interpolations; LCOS and installed held flat outside their published span.
A24: B. Reference class (13 utility-owned comparables, <= 100 MWh)
A25: Project | B25: COD year | C25: Nominal $/kWh | D25: Index at COD | E25: Index 2026 | F25: Factor | G25: 2026$ $/kWh | H25: Naive (whole cost deflated)
A26: Martha's Vineyard BESS Phase 2 (cancelled) | B26: 2019 | C26: 437.5 | D26: =INDEX(CHOOSE($B$6,$B$10:$B$21,$C$10:$C$21,$D$10:$D$21),MATCH(B26,$A$10:$A$21,0)) -> 597 | E26: =INDEX(CHOOSE($B$6,$B$10:$B$21,$C$10:$C$21,$D$10:$D$21),MATCH(2026,$A$10:$A$21,0)) -> 458 | F26: =$B$4*E26/D26+(1-$B$4)*(1+$B$5)^(2026-B26) -> 1.0702352 | G26: =C26*F26 -> 468.22791 | H26: =C26*E26/D26 -> 335.63652
A27: Pomona (Ladentown) BESS | B27: 2021 | C27: 616.7 | D27: =INDEX(CHOOSE($B$6,$B$10:$B$21,$C$10:$C$21,$D$10:$D$21),MATCH(B27,$A$10:$A$21,0)) -> 542 | E27: =INDEX(CHOOSE($B$6,$B$10:$B$21,$C$10:$C$21,$D$10:$D$21),MATCH(2026,$A$10:$A$21,0)) -> 458 | F27: =$B$4*E27/D27+(1-$B$4)*(1+$B$5)^(2026-B27) -> 1.0506192 | G27: =C27*F27 -> 647.91684 | H27: =C27*E27/D27 -> 521.12288
A28: Sterling MLD Chocksett Road BESS | B28: 2016 | C28: 692.3 | D28: =INDEX(CHOOSE($B$6,$B$10:$B$21,$C$10:$C$21,$D$10:$D$21),MATCH(B28,$A$10:$A$21,0)) -> 1493 | E28: =INDEX(CHOOSE($B$6,$B$10:$B$21,$C$10:$C$21,$D$10:$D$21),MATCH(2026,$A$10:$A$21,0)) -> 458 | F28: =$B$4*E28/D28+(1-$B$4)*(1+$B$5)^(2026-B28) -> 0.96906522 | G28: =C28*F28 -> 670.88385 | H28: =C28*E28/D28 -> 212.37334
A29: Martha's Vineyard BESS Phase 1 (cancelled) | B29: 2019 | C29: 750 | D29: =INDEX(CHOOSE($B$6,$B$10:$B$21,$C$10:$C$21,$D$10:$D$21),MATCH(B29,$A$10:$A$21,0)) -> 597 | E29: =INDEX(CHOOSE($B$6,$B$10:$B$21,$C$10:$C$21,$D$10:$D$21),MATCH(2026,$A$10:$A$21,0)) -> 458 | F29: =$B$4*E29/D29+(1-$B$4)*(1+$B$5)^(2026-B29) -> 1.0702352 | G29: =C29*F29 -> 802.67642 | H29: =C29*E29/D29 -> 575.37688
A30: Chugach BESS (Southcentral Power Project site) | B30: 2024 | C30: 812.5 | D30: =INDEX(CHOOSE($B$6,$B$10:$B$21,$C$10:$C$21,$D$10:$D$21),MATCH(B30,$A$10:$A$21,0)) -> 458 | E30: =INDEX(CHOOSE($B$6,$B$10:$B$21,$C$10:$C$21,$D$10:$D$21),MATCH(2026,$A$10:$A$21,0)) -> 458 | F30: =$B$4*E30/D30+(1-$B$4)*(1+$B$5)^(2026-B30) -> 1.042735 | G30: =C30*F30 -> 847.22219 | H30: =C30*E30/D30 -> 812.5
A31: Kingsbery Community Solar + Storage | B31: 2016 | C31: 1000 | D31: =INDEX(CHOOSE($B$6,$B$10:$B$21,$C$10:$C$21,$D$10:$D$21),MATCH(B31,$A$10:$A$21,0)) -> 1493 | E31: =INDEX(CHOOSE($B$6,$B$10:$B$21,$C$10:$C$21,$D$10:$D$21),MATCH(2026,$A$10:$A$21,0)) -> 458 | F31: =$B$4*E31/D31+(1-$B$4)*(1+$B$5)^(2026-B31) -> 0.96906522 | G31: =C31*F31 -> 969.06522 | H31: =C31*E31/D31 -> 306.7649
A32: Stafford Hill Solar + Storage (Rutland) | B32: 2015 | C32: 1235.3 | D32: =INDEX(CHOOSE($B$6,$B$10:$B$21,$C$10:$C$21,$D$10:$D$21),MATCH(B32,$A$10:$A$21,0)) -> 2152 | E32: =INDEX(CHOOSE($B$6,$B$10:$B$21,$C$10:$C$21,$D$10:$D$21),MATCH(2026,$A$10:$A$21,0)) -> 458 | F32: =$B$4*E32/D32+(1-$B$4)*(1+$B$5)^(2026-B32) -> 0.96111194 | G32: =C32*F32 -> 1187.2616 | H32: =C32*E32/D32 -> 262.90307
A33: Ozone Park BESS | B33: 2019 | C33: 1250 | D33: =INDEX(CHOOSE($B$6,$B$10:$B$21,$C$10:$C$21,$D$10:$D$21),MATCH(B33,$A$10:$A$21,0)) -> 597 | E33: =INDEX(CHOOSE($B$6,$B$10:$B$21,$C$10:$C$21,$D$10:$D$21),MATCH(2026,$A$10:$A$21,0)) -> 458 | F33: =$B$4*E33/D33+(1-$B$4)*(1+$B$5)^(2026-B33) -> 1.0702352 | G33: =C33*F33 -> 1337.794 | H33: =C33*E33/D33 -> 958.96147
A34: Harding Street BESS | B34: 2016 | C34: 1250 | D34: =INDEX(CHOOSE($B$6,$B$10:$B$21,$C$10:$C$21,$D$10:$D$21),MATCH(B34,$A$10:$A$21,0)) -> 1493 | E34: =INDEX(CHOOSE($B$6,$B$10:$B$21,$C$10:$C$21,$D$10:$D$21),MATCH(2026,$A$10:$A$21,0)) -> 458 | F34: =$B$4*E34/D34+(1-$B$4)*(1+$B$5)^(2026-B34) -> 0.96906522 | G34: =C34*F34 -> 1211.3315 | H34: =C34*E34/D34 -> 383.45613
A35: Outer Cape (Provincetown) BESS | B35: 2022 | C35: 1289.5 | D35: =INDEX(CHOOSE($B$6,$B$10:$B$21,$C$10:$C$21,$D$10:$D$21),MATCH(B35,$A$10:$A$21,0)) -> 514 | E35: =INDEX(CHOOSE($B$6,$B$10:$B$21,$C$10:$C$21,$D$10:$D$21),MATCH(2026,$A$10:$A$21,0)) -> 458 | F35: =$B$4*E35/D35+(1-$B$4)*(1+$B$5)^(2026-B35) -> 1.044934 | G35: =C35*F35 -> 1347.4424 | H35: =C35*E35/D35 -> 1149.0097
A36: Fairhaven BESS | B36: 2023 | C36: 1659.3 | D36: =INDEX(CHOOSE($B$6,$B$10:$B$21,$C$10:$C$21,$D$10:$D$21),MATCH(B36,$A$10:$A$21,0)) -> 486 | E36: =INDEX(CHOOSE($B$6,$B$10:$B$21,$C$10:$C$21,$D$10:$D$21),MATCH(2026,$A$10:$A$21,0)) -> 458 | F36: =$B$4*E36/D36+(1-$B$4)*(1+$B$5)^(2026-B36) -> 1.0421855 | G36: =C36*F36 -> 1729.2983 | H36: =C36*E36/D36 -> 1563.7025
A37: Glacier BESS | B37: 2016 | C37: 2545.5 | D37: =INDEX(CHOOSE($B$6,$B$10:$B$21,$C$10:$C$21,$D$10:$D$21),MATCH(B37,$A$10:$A$21,0)) -> 1493 | E37: =INDEX(CHOOSE($B$6,$B$10:$B$21,$C$10:$C$21,$D$10:$D$21),MATCH(2026,$A$10:$A$21,0)) -> 458 | F37: =$B$4*E37/D37+(1-$B$4)*(1+$B$5)^(2026-B37) -> 0.96906522 | G37: =C37*F37 -> 2466.7555 | H37: =C37*E37/D37 -> 780.87006
A38: Dalrymple ESCRI BESS [AUSTRALIA] | B38: 2018 | C38: 2775 | D38: =INDEX(CHOOSE($B$6,$B$10:$B$21,$C$10:$C$21,$D$10:$D$21),MATCH(B38,$A$10:$A$21,0)) -> 625 | E38: =INDEX(CHOOSE($B$6,$B$10:$B$21,$C$10:$C$21,$D$10:$D$21),MATCH(2026,$A$10:$A$21,0)) -> 458 | F38: =$B$4*E38/D38+(1-$B$4)*(1+$B$5)^(2026-B38) -> 1.0832054 | G38: =C38*F38 -> 3005.895 | H38: =C38*E38/D38 -> 2033.52
A39: Median | C39: =MEDIAN(C26:C38) -> 1235.3 | G39: =MEDIAN(G26:G38) -> 1187.2616 | H39: =MEDIAN(H26:H38) -> 575.37688
A40: Hyde Park installed $833, percentile | C40: =COUNTIF(C26:C38,"<"&833)/COUNT(C26:C38) -> 0.38461538 | G40: =COUNTIF(G26:G38,"<"&833)/COUNT(G26:G38) -> 0.30769231
A41: Hyde Park station complete direct $1,483, percentile | C41: =COUNTIF(C26:C38,"<"&1483)/COUNT(C26:C38) -> 0.76923077 | G41: =COUNTIF(G26:G38,"<"&1483)/COUNT(G26:G38) -> 0.76923077
A42: Hyde Park approval $2,862, percentile | C42: =COUNTIF(C26:C38,"<"&2862)/COUNT(C26:C38) -> 1 | G42: =COUNTIF(G26:G38,"<"&2862)/COUNT(G26:G38) -> 0.92307692
A44: C. New York distribution-scale cohort (not in the regression; nominal dollars of the year shown)
A45: Project | B45: Owner | C45: MW | D45: MWh | E45: COD year | F45: Cost $ | G45: $/kWh | H45: $/kW | I45: Hours | J45: Cost basis | K45: Confidence | L45: Source
A46: NineDot Arthur Kill Road (two 4.9 MW systems) | B46: NineDot Energy | C46: 9.8 | D46: 39.1 | E46: 2025 | F46: 43384000 | G46: =F46/D46/1000 -> 1109.5652 | H46: =F46/C46/1000 -> 4426.9388 | I46: =D46/C46 -> 3.9897959 | J46: NYCIDA project budget (inducement resolution, Apr 2024) | K46: High | L46: https://edc.nyc/sites/default/files/2025-03/GB%20Arthur%20Kill%20Storage%20LLC%20-%20Inducement%20and%20Authorizing%20Resolution%20April%202024.pdf
A47: Elevate Renewables, 4401 Victory Blvd, Staten Island | B47: Elevate Renewables (ArcLight) | C47: 15.1 | D47: 60.4 | E47: 2025 | F47: 31650000 | G47: =F47/D47/1000 -> 524.00662 | H47: =F47/C47/1000 -> 2096.0265 | I47: =D47/C47 -> 4 | J47: NYCIDA total project cost (public hearing notice, Apr 2024) | K47: High | L47: https://edc.nyc/sites/default/files/2024-03/IDA-Public-Hearing-Notice-April-18-2024.pdf
A48: Soltage Brigis 1A, Maspeth, Queens | B48: Soltage | C48: 5 | D48: 20 | E48: 2025 | F48: 16104493 | G48: =F48/D48/1000 -> 805.22465 | H48: =F48/C48/1000 -> 3220.8986 | I48: =D48/C48 -> 4 | J48: NYCIDA total project cost (public hearing notice, Mar 2024); 4-h duration assumed (MWh not stated) | K48: Medium (cost High; duration assumed) | L48: https://edc.nyc/sites/default/files/2024-02/IDA-Public-Hearing-Notice-March-7-2024-Public-Hearing.pdf
A49: NineDot 28-project NYC portfolio (financing proxy) | B49: NineDot Energy | C49: 124 | D49: 494 | E49: 2027 | F49: 431000000 | G49: =F49/D49/1000 -> 872.46964 | H49: =F49/C49/1000 -> 3475.8065 | I49: =D49/C49 -> 3.983871 | J49: Natixis construction/term loan + tax-credit bridge + LC facility, Feb 2026; a floor on total cost, not the cost itself | K49: Low-Medium (financing, not capex) | L49: https://www.prnewswire.com/news-releases/natixis-corporate--investment-banking-acts-as-sole-lead-arranger-and-bookrunner-for-ninedot-energy-in-431-million-financing-of-28-battery-energy-storage-systems-portfolio-in-new-york-city-302681842.html
A50: NYSERDA retail (<= 5 MW) average total installed cost, 2022-23 installs | B50: NYSERDA program average | E50: 2023 | G50: 567 | J50: New York's 6 GW Energy Storage Roadmap, NYSERDA/DPS, Dec 2022 | K50: High | L50: https://www.nyserda.ny.gov/-/media/Project/Nyserda/Files/Programs/Energy-Storage/ny-6-gw-energy-storage-roadmap.pdf
A51: NYSERDA retail (<= 5 MW) average total installed cost, 2020-21 installs | B51: NYSERDA program average | E51: 2021 | G51: 464 | J51: as above | K51: High | L51: https://www.nyserda.ny.gov/-/media/Project/Nyserda/Files/Programs/Energy-Storage/ny-6-gw-energy-storage-roadmap.pdf
A52: Con Edison two-part test (CESIR), NY-BEST / NYSEIA filing 11 Mar 2026, Case 24-E-0621 | C52: 161 | F52: 21000000 | J52: average interconnection upgrade cost per project across 34 projects after the test; about $4,400/kW | K52: Medium | L52: https://www.utilitydive.com/news/battery-developers-local-officials-ask-new-york-to-roll-back-con-edison-be/815115/
A53: New York distribution-connected cohort assembled after a review comment that many more projects have been built in New York (NineDot Energy and others). Values from search-index excerpts of the cited documents; edc.nyc, nyserda.ny.gov, canarymedia.com and mgrid.org were blocked by the research proxy.

Sheet Statistics
A1: Statistical evaluation results (values from stats_model.py and mc_model.py, 29 Sep 2026)
A3: Reference class: utility-owned, <=100 MWh
A4: n | B4: 13
A5: Median $/kWh | B5: 1235.2941
A6: Q25 $/kWh | B6: 750
A7: Q75 $/kWh | B7: 1289.4737
A8: Min $/kWh | B8: 437.5
A9: Max $/kWh | B9: 2775
A10: Hyde Park percentile in class: Vendor contract $605 | B10: 0.076923077
A11: Hyde Park percentile in class: Battery installed $833 | B11: 0.38461538
A12: Hyde Park percentile in class: Station complete, direct $1,483 | B12: 0.76923077
A13: Hyde Park percentile in class: Approval level $2,862 | B13: 1
A15: Regression: ln($/kWh) ~ ln(MWh) + ln(duration) + year (OLS, HC1 errors)
A16: n | B16: 26
A17: R-squared | B17: 0.64507334
A18: Adjusted R-squared | B18: 0.59667425
A19: Residual SD (log) | B19: 0.36101067
A20: Intercept: coefficient | B20: 7.6193823 | C20: SE 0.252, p = 0.000
A21: Size elasticity (ln MWh): coefficient | B21: -0.17311256 | C21: SE 0.069, p = 0.012
A22: Duration elasticity (ln hours): coefficient | B22: -0.29237933 | C22: SE 0.122, p = 0.016
A23: Year (per year after 2020): coefficient | B23: 0.014875516 | C23: SE 0.036, p = 0.678
A24: Prediction for 20 MWh, 2-h, 2028: P50 $/kWh | B24: 1115.5755
A25: 80% prediction interval, low | B25: 611.09376
A26: 80% prediction interval, high | B26: 2036.5265
A27: Hyde Park percentile of predictive distribution: Vendor contract | B27: 0.096477923
A28: Hyde Park percentile of predictive distribution: Battery installed | B28: 0.26689851
A29: Hyde Park percentile of predictive distribution: Station complete, direct | B29: 0.72795776
A30: Hyde Park percentile of predictive distribution: Approval level | B30: 0.97759643
A32: Monte Carlo on cost layers (20,000 trials; risk register and contingency not added on top)
A33: Base ranges: P10 total ($) | B33: 48910800
A34: Base ranges: P50 total ($) | B34: 51293415
A35: Base ranges: P80 total ($) | B35: 53040843
A36: Base ranges: P90 total ($) | B36: 53991967
A37: Base ranges: reserve to reach P80 above deterministic base ($) | B37: 3376816 | C37: carried risk + contingency = $7,583,517
A38: Base ranges: probability total exceeds $57.2M approval level | B38: 0.0031
A39: Base ranges: battery contract share, P50 | B39: 0.24238635
A40: Wide (Class 5-like) ranges: P10 total ($) | B40: 50163522
A41: Wide (Class 5-like) ranges: P50 total ($) | B41: 53420558
A42: Wide (Class 5-like) ranges: P80 total ($) | B42: 55912637
A43: Wide (Class 5-like) ranges: P90 total ($) | B43: 57312479
A44: Wide (Class 5-like) ranges: reserve to reach P80 above deterministic base ($) | B44: 6248610.5 | C44: carried risk + contingency = $7,583,517
A45: Wide (Class 5-like) ranges: probability total exceeds $57.2M approval level | B45: 0.10365
A46: Wide (Class 5-like) ranges: battery contract share, P50 | B46: 0.23403028
A48: Layer standard deviation, $ (base / wide)
A49: Layer A | B49: 173279.18 | C49: wide: 239,415
A50: Layer B | B50: 326886.1 | C50: wide: 465,344
A51: Layer C | B51: 176401.13 | C51: wide: 238,386
A52: Layer D | B52: 456422.88 | C52: wide: 617,589
A53: Layer E | B53: 934979.62 | C53: wide: 1,311,665
A54: Layer F | B54: 799004.55 | C54: wide: 1,076,023
A55: Layer G | B55: 159057.49 | C55: wide: 217,468
A56: Layer H | B56: 514608.69 | C56: wide: 742,591
A57: Layer I | B57: 43557.151 | C57: wide: 58,740

Sheet Line Items
A1: Estimate | B1: CBS1 | C1: CBS4 | D1: Seq | E1: Description | F1: Qty | G1: Unit | H1: Direct Cost ($) | I1: Manhours | J1: Note | K1: Layer | L1: Layer code
A2: Hyde Park BESS - Sta. 496 - Rev 2 | B2: 03 | C2: 03.01.00.00 | D2: 0 | E2: SCS, Internal, Traditional | F2: 1 | G2: ls | H2: 5456.8722 | I2: 0 | K2: F. Station 496 feeder protection upgrades (interconnection) | L2: =LEFT(K2,1) -> F
A3: Hyde Park BESS - Sta. 496 - Rev 2 | B3: 03 | C3: 03.02.00.00 | D3: 0 | E3: SCS, External, Traditional | F3: 1 | G3: ls | H3: 8185.3083 | I3: 0 | K3: F. Station 496 feeder protection upgrades (interconnection) | L3: =LEFT(K3,1) -> F
A4: Hyde Park BESS - Sta. 496 - Rev 2 | B4: 04 | C4: 04.01.00.00 | D4: 0 | E4: Siting, Internal, Application | F4: 1 | G4: ls | H4: 17393.78 | I4: 0 | K4: F. Station 496 feeder protection upgrades (interconnection) | L4: =LEFT(K4,1) -> F
A5: Hyde Park BESS - Sta. 496 - Rev 2 | B5: 04 | C5: 04.02.00.00 | D5: 0 | E5: Siting, External, Application | F5: 1 | G5: ls | H5: 156544.02 | I5: 0 | K5: F. Station 496 feeder protection upgrades (interconnection) | L5: =LEFT(K5,1) -> F
A6: Hyde Park BESS - Sta. 496 - Rev 2 | B6: 05 | C6: 05.02.01.00 | D6: 238 | E6: Engr. Station - Eversource | F6: 40 | G6: mh | H6: 2719.5623 | I6: 40 | K6: F. Station 496 feeder protection upgrades (interconnection) | L6: =LEFT(K6,1) -> F
A7: Hyde Park BESS - Sta. 496 - Rev 2 | B7: 05 | C7: 05.02.02.00 | D7: 239 | E7: Engr. Station - Contractor | F7: 120 | G7: mh | H7: 21359.491 | I7: 120 | K7: F. Station 496 feeder protection upgrades (interconnection) | L7: =LEFT(K7,1) -> F
A8: Hyde Park BESS - Sta. 496 - Rev 2 | B8: 05 | C8: 05.04.01.00 | D8: 242 | E8: Engr. P&C - Eversource | F8: 80 | G8: mh | H8: 5439.1246 | I8: 80 | K8: F. Station 496 feeder protection upgrades (interconnection) | L8: =LEFT(K8,1) -> F
A9: Hyde Park BESS - Sta. 496 - Rev 2 | B9: 05 | C9: 05.04.02.00 | D9: 243 | E9: Engr. P&C - Contractor | F9: 160 | G9: mh | H9: 28832.217 | I9: 160 | K9: F. Station 496 feeder protection upgrades (interconnection) | L9: =LEFT(K9,1) -> F
A10: Hyde Park BESS - Sta. 496 - Rev 2 | B10: 05 | C10: 05.07.01.00 | D10: 247 | E10: Engr. SS Drafting/Project Services - Eversource | F10: 40 | G10: mh | H10: 2817.0942 | I10: 40 | K10: F. Station 496 feeder protection upgrades (interconnection) | L10: =LEFT(K10,1) -> F
A11: Hyde Park BESS - Sta. 496 - Rev 2 | B11: 06 | C11: 06.04.02.00 | D11: 480 | E11: Miscellaneous Cabinet/ Devices Panel Plate Repacments, (Furnish) | F11: 8 | G11: ea | H11: 6371.4181 | I11: 0 | K11: F. Station 496 feeder protection upgrades (interconnection) | L11: =LEFT(K11,1) -> F
A12: Hyde Park BESS - Sta. 496 - Rev 2 | B12: 06 | C12: 06.04.02.00 | D12: 478 | E12: Relays AAB FT-1 9R Test Device, (Furnish) | F12: 40 | G12: ea | H12: 29202.333 | I12: 0 | K12: F. Station 496 feeder protection upgrades (interconnection) | L12: =LEFT(K12,1) -> F
A13: Hyde Park BESS - Sta. 496 - Rev 2 | B13: 06 | C13: 06.04.02.00 | D13: 470 | E13: Relays SEL-351S (Transformer and Feeder Protection), (Furnish) | F13: 8 | G13: ea | H13: 40639.028 | I13: 0 | K13: F. Station 496 feeder protection upgrades (interconnection) | L13: =LEFT(K13,1) -> F
... A19: Hyde Park BESS - Sta. 496 - Rev 2 | B19: 06 | C19: 06.04.03.00 | D19: 484 | E19: Insulated Control Cable Cable, Control, Lug, Termination #18-14 AWG, (Furnish) | F19: 100 | G19: ea | H19: 70.351074 | I19: 0 | K19: F. Station 496 feeder protection upgrades (interconnection) | L19: =LEFT(K19,1) -> F
A20: Hyde Park BESS - Sta. 496 - Rev 2 | B20: 06 | C20: 06.04.03.00 | D20: 298 | E20: Insulated Control Cable Cable, Control, User Defined, (Furnish) | F20: 10000 | G20: lf | H20: 19578.837 | I20: 0 | J20: Length per Estimator | K20: F. Station 496 feeder protection upgrades (interconnection) | L20: =LEFT(K20,1) -> F
A21: Hyde Park BESS - Sta. 496 - Rev 2 | B21: 07 | C21: 07.01.02.01 | D21: 132 | E21: Switching & Tagging (Internal labor) | F21: 320 | G21: mh | H21: 21146.708 | I21: 320 | J21: 20 ops x 8 hrs/ops x 2 switchers | K21: F. Station 496 feeder protection upgrades (interconnection) | L21: =LEFT(K21,1) -> F
A22: Hyde Park BESS - Sta. 496 - Rev 2 | B22: 07 | C22: 07.01.04.00 | D22: 0 | E22: Demobilization | F22: 1 | G22: ls | H22: 33081.577 | I22: 0 | K22: F. Station 496 feeder protection upgrades (interconnection) | L22: =LEFT(K22,1) -> F
A23: Hyde Park BESS - Sta. 496 - Rev 2 | B23: 07 | C23: 07.01.04.00 | D23: 0 | E23: Mobilization | F23: 1 | G23: ls | H23: 33081.577 | I23: 0 | K23: F. Station 496 feeder protection upgrades (interconnection) | L23: =LEFT(K23,1) -> F
A24: Hyde Park BESS - Sta. 496 - Rev 2 | B24: 07 | C24: 07.03.02.12 | D24: 489 | E24: Insulated Control Cable Cable, Control, #12 SIS Switchbourd cable , (Install) | F24: 200 | G24: lf | H24: 230.7988 | I24: 1.2 | K24: F. Station 496 feeder protection upgrades (interconnection) | L24: =LEFT(K24,1) -> F
A25: Hyde Park BESS - Sta. 496 - Rev 2 | B25: 07 | C25: 07.03.02.12 | D25: 487 | E25: Insulated Control Cable Cable, Control, #14 SIS Switchbourd cable , (Install) | F25: 200 | G25: lf | H25: 192.33056 | I25: 1 | K25: F. Station 496 feeder protection upgrades (interconnection) | L25: =LEFT(K25,1) -> F
A26: Hyde Park BESS - Sta. 496 - Rev 2 | B26: 07 | C26: 07.03.02.12 | D26: 483 | E26: Insulated Control Cable Cable, Control, Lug, Termination #12-10 AWG , (Install) | F26: 100 | G26: ea | H26: 2307.9667 | I26: 12 | K26: F. Station 496 feeder protection upgrades (interconnection) | L26: =LEFT(K26,1) -> F
A27: Hyde Park BESS - Sta. 496 - Rev 2 | B27: 07 | C27: 07.03.02.12 | D27: 485 | E27: Insulated Control Cable Cable, Control, Lug, Termination #18-14 AWG, (Install) | F27: 100 | G27: ea | H27: 1538.6445 | I27: 8 | K27: F. Station 496 feeder protection upgrades (interconnection) | L27: =LEFT(K27,1) -> F
A28: Hyde Park BESS - Sta. 496 - Rev 2 | B28: 07 | C28: 07.03.02.12 | D28: 299 | E28: Insulated Control Cable Cable, Control, User Defined, (Install) | F28: 10000 | G28: lf | H28: 46159.335 | I28: 240 | J28: Length per Estimator | K28: F. Station 496 feeder protection upgrades (interconnection) | L28: =LEFT(K28,1) -> F
A29: Hyde Park BESS - Sta. 496 - Rev 2 | B29: 07 | C29: 07.03.03.02 | D29: 481 | E29: Miscellaneous Cabinet/ Devices Panel Plate Repacments, (Install) | F29: 8 | G29: ea | H29: 1538.6445 | I29: 8 | K29: F. Station 496 feeder protection upgrades (interconnection) | L29: =LEFT(K29,1) -> F
A30: Hyde Park BESS - Sta. 496 - Rev 2 | B30: 07 | C30: 07.03.03.02 | D30: 479 | E30: Relays AAB FT-1 9R Test Device, (Install) | F30: 40 | G30: ea | H30: 19233.056 | I30: 100 | K30: F. Station 496 feeder protection upgrades (interconnection) | L30: =LEFT(K30,1) -> F
A31: Hyde Park BESS - Sta. 496 - Rev 2 | B31: 07 | C31: 07.03.03.02 | D31: 471 | E31: Relays SEL-351S (Transformer and Feeder Protection), (Install) | F31: 8 | G31: ea | H31: 492366.24 | I31: 2560 | K31: F. Station 496 feeder protection upgrades (interconnection) | L31: =LEFT(K31,1) -> F
A32: Hyde Park BESS - Sta. 496 - Rev 2 | B32: 07 | C32: 07.03.03.02 | D32: 477 | E32: Relays SEL-735 (Transformer Protection), (Install) | F32: 4 | G32: ea | H32: 246183.12 | I32: 1280 | K32: F. Station 496 feeder protection upgrades (interconnection) | L32: =LEFT(K32,1) -> F
A33: Hyde Park BESS - Sta. 496 - Rev 2 | B33: 07 | C33: 07.03.03.02 | D33: 473 | E33: Relays SEL-751 (Transformer and Feeder Protection), (Install) | F33: 8 | G33: ea | H33: 492366.24 | I33: 2560 | K33: F. Station 496 feeder protection upgrades (interconnection) | L33: =LEFT(K33,1) -> F
A34: Hyde Park BESS - Sta. 496 - Rev 2 | B34: 08 | C34: 08.01.02.00 | D34: 138 | E34: Lead Commissioning Engr. (LCE), Contractor | F34: 2600 | G34: mh | H34: 663104.94 | I34: 2600 | J34: 50% mhrs of Field Test Engr. | K34: F. Station 496 feeder protection upgrades (interconnection) | L34: =LEFT(K34,1) -> F
A35: Hyde Park BESS - Sta. 496 - Rev 2 | B35: 08 | C35: 08.02.02.00 | D35: 140 | E35: Field Test Engr., Contractor | F35: 5200 | G35: mh | H35: 1151386.3 | I35: 5200 | J35: SEL-751 8 reloays x 300 mhrs per RRA = 2,400 mhrs SEL-735 4 reloays x 300 mhrs per RRA = 1,200 mhrs SEL-351S 8 reloays x 420 mhrs per RRA = 3,360 mhrs Total = 6,920 mhrs x 75% efficiency = 5,200 mhrs | K35: F. Station 496 feeder protection upgrades (interconnection) | L35: =LEFT(K35,1) -> F
A36: Hyde Park BESS - Sta. 496 - Rev 2 | B36: 09 | C36: 09.01.02.00 | D36: 148 | E36: Project Manager, Contractor | F36: 138 | G36: mh | H36: 25029.792 | I36: 138 | J36: 4 mns x 4.3 wks/mn x 8 mhrs/wk | K36: F. Station 496 feeder protection upgrades (interconnection) | L36: =LEFT(K36,1) -> F
A37: Hyde Park BESS - Sta. 496 - Rev 2 | B37: 09 | C37: 09.03.01.00 | D37: 149 | E37: Purchasing, Eversource | F37: 24 | G37: mh | H37: 1790.1008 | I37: 24 | K37: F. Station 496 feeder protection upgrades (interconnection) | L37: =LEFT(K37,1) -> F
A38: Hyde Park BESS - Sta. 496 - Rev 2 | B38: 09 | C38: 09.04.01.00 | D38: 167 | E38: System Planning, Eversource | F38: 40 | G38: mh | H38: 3104.7161 | I38: 40 | K38: F. Station 496 feeder protection upgrades (interconnection) | L38: =LEFT(K38,1) -> F
A39: Hyde Park BESS - Sta. 496 - Rev 2 | B39: 09 | C39: 09.08.01.00 | D39: 159 | E39: Estimating, Eversource | F39: 40 | G39: mh | H39: 2705.7181 | I39: 40 | K39: F. Station 496 feeder protection upgrades (interconnection) | L39: =LEFT(K39,1) -> F
A40: Hyde Park BESS - Sta. 496 - Rev 2 | B40: 09 | C40: 09.09.01.00 | D40: 157 | E40: Project Controls, Project Performance, Eversource | F40: 24 | G40: mh | H40: 1278.1306 | I40: 24 | K40: F. Station 496 feeder protection upgrades (interconnection) | L40: =LEFT(K40,1) -> F
A41: Hyde Park BESS - Sta. 496 - Rev 2 | B41: 09 | C41: 09.09.01.00 | D41: 155 | E41: Project Controls, Scheduling, Eversource | F41: 24 | G41: mh | H41: 1278.1306 | I41: 24 | K41: F. Station 496 feeder protection upgrades (interconnection) | L41: =LEFT(K41,1) -> F
A42: Hyde Park BESS - Sta. 496 - Rev 2 | B42: 09 | C42: 09.10.01.00 | D42: 161 | E42: Asset Management, Eversource | F42: 40 | G42: mh | H42: 2568.9001 | I42: 40 | K42: F. Station 496 feeder protection upgrades (interconnection) | L42: =LEFT(K42,1) -> F
A43: Hyde Park BESS - Sta. 496 - Rev 2 | B43: 09 | C43: 09.11.01.00 | D43: 452 | E43: Construction Manager (CR), Eversource | F43: 344 | G43: mh | H43: 59170.19 | I43: 344 | J43: 2mns x 4.3wks/mn x 40 mhrs/wk | K43: F. Station 496 feeder protection upgrades (interconnection) | L43: =LEFT(K43,1) -> F
A44: Hyde Park BESS - Sta. 496 - Rev 2 | B44: 10 | C44: 10.01.00.00 | D44: 475 | E44: Removals - Station - ABB-REF610 Relays (Labor) | F44: 8 | G44: ea | H44: 49236.624 | I44: 256 | J44: 10% of install (320 mhrs) | K44: F. Station 496 feeder protection upgrades (interconnection) | L44: =LEFT(K44,1) -> F
A45: Hyde Park BESS - Sta. 496 - Rev 2 | B45: 10 | C45: 10.01.00.00 | D45: 474 | E45: Removals - Station - SEL-551 Relays (Labor) | F45: 8 | G45: ea | H45: 49236.624 | I45: 256 | J45: 10% of install (320 mhrs) | K45: F. Station 496 feeder protection upgrades (interconnection) | L45: =LEFT(K45,1) -> F
A46: Hyde Park BESS - Sta. 496 - Rev 2 | B46: 10 | C46: 10.01.00.00 | D46: 491 | E46: Removals - Station - Test Switches (Labor) | F46: 40 | G46: ea | H46: 9616.5281 | I46: 50 | J46: 50% of install (2.5 mhrs) | K46: F. Station 496 feeder protection upgrades (interconnection) | L46: =LEFT(K46,1) -> F
A47: Hyde Park BESS - Sta. 496 - Rev 2 | B47: 10 | C47: 10.01.00.00 | D47: 492 | E47: Removals - Station - Wiring (Labor) | F47: 1 | G47: ea | H47: 15386.445 | I47: 80 | J47: 2 elec x 1 wk x 40 mhrs/wk | K47: F. Station 496 feeder protection upgrades (interconnection) | L47: =LEFT(K47,1) -> F
A48: Hyde Park BESS - Sta. 496 - Rev 2 | B48: 11 | C48: 11.00.00.03 | D48: 0 | E48: CWIPDistribution | F48: 1 | G48: ls | H48: 76400.073 | I48: 0 | K48: F. Station 496 feeder protection upgrades (interconnection) | L48: =LEFT(K48,1) -> F
A49: Hyde Park BESS - Sta. 496 - Rev 2 | B49: 12 | C49: 12.07.00.00 | D49: 455 | E49: Risk - Construction - Design / Scope changes | F49: 1 | G49: ls | H49: 200000 | I49: 0 | J49: Change orders, increase labor and materials costs. | K49: F. Station 496 feeder protection upgrades (interconnection) | L49: =LEFT(K49,1) -> F
A50: Hyde Park BESS - Sta. 496 - Rev 2 | B50: 12 | C50: 12.07.00.00 | D50: 461 | E50: Risk - Construction - Labor costs impact | F50: 1 | G50: ls | H50: 220000 | I50: 0 | J50: Salaries increase yearly or a labor shortage of qualified personnel. Possible overtime. | K50: F. Station 496 feeder protection upgrades (interconnection) | L50: =LEFT(K50,1) -> F
A51: Hyde Park BESS - Sta. 496 - Rev 2 | B51: 12 | C51: 12.07.00.00 | D51: 460 | E51: Risk - Construction - Mat'l costs impact | F51: 1 | G51: ls | H51: 300000 | I51: 0 | J51: Material costs increase especially precious metals and possible tariffs. | K51: F. Station 496 feeder protection upgrades (interconnection) | L51: =LEFT(K51,1) -> F
A52: Hyde Park BESS - Sta. 496 - Rev 2 | B52: 12 | C52: 12.07.00.00 | D52: 454 | E52: Risk - Construction - Weather delays imact | F52: 1 | G52: ls | H52: 50000 | I52: 0 | J52: Delay in schedule due to adverse weather. | K52: F. Station 496 feeder protection upgrades (interconnection) | L52: =LEFT(K52,1) -> F
A53: Hyde Park BESS - Sta. 496 - Rev 2 | B53: 13 | C53: 13.01.00.00 | D53: 0 | E53: Indirect - Non-Productive Basis | F53: 1 | G53: ls | H53: 55403.688 | I53: 0 | K53: F. Station 496 feeder protection upgrades (interconnection) | L53: =LEFT(K53,1) -> F
A54: Hyde Park BESS - Sta. 496 - Rev 2 | B54: 13 | C54: 13.02.00.00 | D54: 0 | E54: Indirect - Payroll Benefit Basis | F54: 1 | G54: ls | H54: 26548.677 | I54: 0 | K54: F. Station 496 feeder protection upgrades (interconnection) | L54: =LEFT(K54,1) -> F
A55: Hyde Park BESS - Sta. 496 - Rev 2 | B55: 13 | C55: 13.03.00.00 | D55: 0 | E55: Indirect - Gen Svc Co OH Basis | F55: 1 | G55: ls | H55: 10600.505 | I55: 0 | K55: F. Station 496 feeder protection upgrades (interconnection) | L55: =LEFT(K55,1) -> F
A56: Hyde Park BESS - Sta. 496 - Rev 2 | B56: 13 | C56: 13.05.00.00 | D56: 0 | E56: Indirect - E&S Station Basis | F56: 1 | G56: ls | H56: 1458437.2 | I56: 0 | K56: F. Station 496 feeder protection upgrades (interconnection) | L56: =LEFT(K56,1) -> F
A57: Hyde Park BESS - Sta. 496 - Rev 2 | B57: 13 | C57: 13.06.00.00 | D57: 0 | E57: Indirect - AS & E Basis | F57: 1 | G57: ls | H57: 58085.038 | I57: 0 | K57: F. Station 496 feeder protection upgrades (interconnection) | L57: =LEFT(K57,1) -> F
A58: Hyde Park BESS - Sta. 496 - Rev 2 | B58: 13 | C58: 13.08.00.00 | D58: 0 | E58: Indirect - Lobby Stock Basis | F58: 1 | G58: ls | H58: 0 | I58: 0 | K58: F. Station 496 feeder protection upgrades (interconnection) | L58: =LEFT(K58,1) -> F
A59: Hyde Park BESS - Sta. 496 - Rev 2 | B59: 13 | C59: 13.09.00.00 | D59: 0 | E59: Indirect - MDEC Basis | F59: 1 | G59: ls | H59: 248747.8 | I59: 0 | K59: F. Station 496 feeder protection upgrades (interconnection) | L59: =LEFT(K59,1) -> F
A60: Hyde Park BESS - Sta. 496 - Rev 2 | B60: 13 | C60: 13.10.00.00 | D60: 0 | E60: Indirect - Vehicles OH Basis | F60: 1 | G60: ls | H60: 64151.639 | I60: 0 | K60: F. Station 496 feeder protection upgrades (interconnection) | L60: =LEFT(K60,1) -> F
A61: Hyde Park BESS - Sta. 496 - Rev 2 | B61: 14 | C61: 14.01.00.00 | D61: 0 | E61: AFUDC | F61: 1 | G61: ls | H61: 333060.49 | I61: 0 | K61: F. Station 496 feeder protection upgrades (interconnection) | L61: =LEFT(K61,1) -> F
A62: Hyde Park BESS - Sta. 496 - Rev 2 | B62: 15 | C62: 15.15.00.00 | D62: 217 | E62: Contingency - General | F62: 1 | G62: ls | H62: 331723 | I62: 0 | K62: F. Station 496 feeder protection upgrades (interconnection) | L62: =LEFT(K62,1) -> F
A63: Hyde Park BESS - Sta. 360 - Rev 3 | B63: 01 | C63: 01.04.00.00 | D63: 85 | E63: Contractor ROW, Easment Costs | F63: 1 | G63: ls | H63: 2532 | I63: 0 | J63: Actual Costs to 9/23/26 | K63: H. Owner soft costs (engineering, siting, environmental, outreach, PM, land) | L63: =LEFT(K63,1) -> H
A64: Hyde Park BESS - Sta. 360 - Rev 3 | B64: 01 | C64: 01.04.00.00 | D64: 84 | E64: Land Costs | F64: 1 | G64: ls | H64: 578.37 | I64: 0 | J64: Actual Costs to 9/23/26 | K64: H. Owner soft costs (engineering, siting, environmental, outreach, PM, land) | L64: =LEFT(K64,1) -> H
A65: Hyde Park BESS - Sta. 360 - Rev 3 | B65: 02 | C65: 02.01.00.00 | D65: 93 | E65: Enviromental, Eversource | F65: 160 | G65: mh | H65: 9793.5143 | I65: 160 | J65: Mhrs from E-23-373 estimate | K65: H. Owner soft costs (engineering, siting, environmental, outreach, PM, land) | L65: =LEFT(K65,1) -> H
A66: Hyde Park BESS - Sta. 360 - Rev 3 | B66: 02 | C66: 02.02.00.00 | D66: 346 | E66: City/Municipal Permits (Zoning, Building, etc.) | F66: 40 | G66: ea | H66: 7096.726 | I66: 40 | J66: Zoning relief and permits. City of Boston Article 80 & zoning variance. | K66: H. Owner soft costs (engineering, siting, environmental, outreach, PM, land) | L66: =LEFT(K66,1) -> H
A67: Hyde Park BESS - Sta. 360 - Rev 3 | B67: 02 | C67: 02.02.00.00 | D67: 345 | E67: DEP Listed Site - Wast Management | F67: 40 | G67: ea | H67: 7096.726 | I67: 40 | J67: Permit needed for authorization to construct on closed landfill facility. | K67: H. Owner soft costs (engineering, siting, environmental, outreach, PM, land) | L67: =LEFT(K67,1) -> H
A68: Hyde Park BESS - Sta. 360 - Rev 3 | B68: 02 | C68: 02.02.00.00 | D68: 350 | E68: eNOI, EPA 2022, Submittal | F68: 24 | G68: ea | H68: 4258.0356 | I68: 24 | J68: Disturb greater than 1 acre of land. | K68: H. Owner soft costs (engineering, siting, environmental, outreach, PM, land) | L68: =LEFT(K68,1) -> H
A69: Hyde Park BESS - Sta. 360 - Rev 3 | B69: 02 | C69: 02.02.00.00 | D69: 94 | E69: Environmental, Contractor | F69: 160 | G69: mh | H69: 28386.904 | I69: 160 | J69: Mhrs from E-23-373 estimate | K69: H. Owner soft costs (engineering, siting, environmental, outreach, PM, land) | L69: =LEFT(K69,1) -> H
A70: Hyde Park BESS - Sta. 360 - Rev 3 | B70: 02 | C70: 02.02.00.00 | D70: 348 | E70: Mass DEP | F70: 24 | G70: ea | H70: 4258.0356 | I70: 24 | J70: Tier II reporting for batteries. | K70: H. Owner soft costs (engineering, siting, environmental, outreach, PM, land) | L70: =LEFT(K70,1) -> H
A71: Hyde Park BESS - Sta. 360 - Rev 3 | B71: 02 | C71: 02.02.00.00 | D71: 347 | E71: Soil Sampling/Disposal | F71: 120 | G71: ea | H71: 23141.074 | I71: 120 | J71: Samples plus soil management plan needed. | K71: H. Owner soft costs (engineering, siting, environmental, outreach, PM, land) | L71: =LEFT(K71,1) -> H
A72: Hyde Park BESS - Sta. 360 - Rev 3 | B72: 02 | C72: 02.02.00.00 | D72: 349 | E72: Storm Water Pollution Prevention Plan (SWPPP) | F72: 80 | G72: ea | H72: 14193.452 | I72: 80 | J72: Develop plan and inspections are required. | K72: H. Owner soft costs (engineering, siting, environmental, outreach, PM, land) | L72: =LEFT(K72,1) -> H
A73: Hyde Park BESS - Sta. 360 - Rev 3 | B73: 02 | C73: 02.03.01.00 | D73: 88 | E73: Legal, Environmental, Eversource | F73: 1 | G73: ls | H73: 70700.04 | I73: 0 | J73: Actual Costs to 9/23/26 | K73: H. Owner soft costs (engineering, siting, environmental, outreach, PM, land) | L73: =LEFT(K73,1) -> H
A74: Hyde Park BESS - Sta. 360 - Rev 3 | B74: 02 | C74: 02.05.00.00 | D74: 92 | E74: Fees - Environmental Permits - Contractor | F74: 1 | G74: ls | H74: 10302.56 | I74: 0 | J74: Actual Costs to 9/23/26 | K74: H. Owner soft costs (engineering, siting, environmental, outreach, PM, land) | L74: =LEFT(K74,1) -> H
A75: Hyde Park BESS - Sta. 360 - Rev 3 | B75: 03 | C75: 03.01.00.00 | D75: 201 | E75: Project Services (Outreach), Eversource (Actuals input) | F75: 1 | G75: ls | H75: 81346.44 | I75: 0 | J75: Actual Costs to 9/23/26 | K75: H. Owner soft costs (engineering, siting, environmental, outreach, PM, land) | L75: =LEFT(K75,1) -> H
A76: Hyde Park BESS - Sta. 360 - Rev 3 | B76: 03 | C76: 03.01.00.00 | D76: 203 | E76: Project Services (Outreach), Eversource (Manual input) | F76: 480 | G76: mh | H76: 29380.543 | I76: 480 | K76: H. Owner soft costs (engineering, siting, environmental, outreach, PM, land) | L76: =LEFT(K76,1) -> H
A77: Hyde Park BESS - Sta. 360 - Rev 3 | B77: 03 | C77: 03.01.00.00 | D77: 0 | E77: SCS, Internal, Traditional | F77: 1 | G77: ls | H77: 36676.052 | I77: 0 | K77: H. Owner soft costs (engineering, siting, environmental, outreach, PM, land) | L77: =LEFT(K77,1) -> H
A78: Hyde Park BESS - Sta. 360 - Rev 3 | B78: 03 | C78: 03.02.00.00 | D78: 202 | E78: Project Services (Outreach), Contractor (Actuals input) | F78: 1 | G78: ls | H78: 3454.72 | I78: 0 | J78: Actual Costs to 9/23/26 | K78: H. Owner soft costs (engineering, siting, environmental, outreach, PM, land) | L78: =LEFT(K78,1) -> H
A79: Hyde Park BESS - Sta. 360 - Rev 3 | B79: 03 | C79: 03.02.00.00 | D79: 204 | E79: Project Services (Outreach), Contractor (Manual input) | F79: 480 | G79: mh | H79: 85160.712 | I79: 480 | K79: H. Owner soft costs (engineering, siting, environmental, outreach, PM, land) | L79: =LEFT(K79,1) -> H
A80: Hyde Park BESS - Sta. 360 - Rev 3 | B80: 03 | C80: 03.02.00.00 | D80: 0 | E80: SCS, External, Traditional | F80: 1 | G80: ls | H80: 55014.078 | I80: 0 | K80: H. Owner soft costs (engineering, siting, environmental, outreach, PM, land) | L80: =LEFT(K80,1) -> H
A81: Hyde Park BESS - Sta. 360 - Rev 3 | B81: 04 | C81: 04.01.00.00 | D81: 197 | E81: Siting, Eversource (Actuals input) | F81: 1 | G81: ls | H81: 68307.72 | I81: 0 | J81: Actual Costs to 9/23/26 | K81: H. Owner soft costs (engineering, siting, environmental, outreach, PM, land) | L81: =LEFT(K81,1) -> H
A82: Hyde Park BESS - Sta. 360 - Rev 3 | B82: 04 | C82: 04.01.00.00 | D82: 193 | E82: Siting, Eversource (Manual input) | F82: 180 | G82: mh | H82: 11656.993 | I82: 180 | J82: Neighborhood is concerned about losing land and visual concerns near shopping plaza. Screening/buffering likely for abutting residential neighborhood. Increase traffic concerns. | K82: H. Owner soft costs (engineering, siting, environmental, outreach, PM, land) | L82: =LEFT(K82,1) -> H
A83: Hyde Park BESS - Sta. 360 - Rev 3 | B83: 04 | C83: 04.01.00.00 | D83: 0 | E83: Siting, Internal, Application | F83: 1 | G83: ls | H83: 116904.92 | I83: 0 | K83: H. Owner soft costs (engineering, siting, environmental, outreach, PM, land) | L83: =LEFT(K83,1) -> H
A84: Hyde Park BESS - Sta. 360 - Rev 3 | B84: 04 | C84: 04.02.00.00 | D84: 198 | E84: Siting, Contractor (Actuals input) | F84: 1 | G84: ls | H84: 6595 | I84: 0 | J84: Actual Costs to 9/23/26 | K84: H. Owner soft costs (engineering, siting, environmental, outreach, PM, land) | L84: =LEFT(K84,1) -> H
A85: Hyde Park BESS - Sta. 360 - Rev 3 | B85: 04 | C85: 04.02.00.00 | D85: 0 | E85: Siting, External, Application | F85: 1 | G85: ls | H85: 1052144.2 | I85: 0 | K85: H. Owner soft costs (engineering, siting, environmental, outreach, PM, land) | L85: =LEFT(K85,1) -> H
A86: Hyde Park BESS - Sta. 360 - Rev 3 | B86: 05 | C86: 05.01.01.00 | D86: 106 | E86: Engr. Civil - Eversource - station | F86: 80 | G86: mh | H86: 5634.1885 | I86: 80 | J86: Costs per email dated 9/18/26, Eng. Costs total $501,000 | K86: H. Owner soft costs (engineering, siting, environmental, outreach, PM, land) | L86: =LEFT(K86,1) -> H
A87: Hyde Park BESS - Sta. 360 - Rev 3 | B87: 05 | C87: 05.01.02.00 | D87: 107 | E87: Engr. Civil - Contractor - station | F87: 80 | G87: mh | H87: 14151.437 | I87: 80 | J87: Costs per email dated 9/18/26, Eng. Costs total $501,000 | K87: H. Owner soft costs (engineering, siting, environmental, outreach, PM, land) | L87: =LEFT(K87,1) -> H
A88: Hyde Park BESS - Sta. 360 - Rev 3 | B88: 05 | C88: 05.01.02.00 | D88: 437 | E88: Engr. Civil - Contractor - station | F88: 1 | G88: ls | H88: 32190.27 | I88: 0 | J88: Actual Costs to 9/23/26 | K88: H. Owner soft costs (engineering, siting, environmental, outreach, PM, land) | L88: =LEFT(K88,1) -> H
A89: Hyde Park BESS - Sta. 360 - Rev 3 | B89: 05 | C89: 05.02.01.00 | D89: 238 | E89: Engr. Station - Eversource | F89: 360 | G89: mh | H89: 24476.061 | I89: 360 | J89: Costs per email dated 9/18/26, Eng. Costs total $501,000 | K89: H. Owner soft costs (engineering, siting, environmental, outreach, PM, land) | L89: =LEFT(K89,1) -> H
A90: Hyde Park BESS - Sta. 360 - Rev 3 | B90: 05 | C90: 05.02.01.00 | D90: 439 | E90: Engr. Station - Eversource | F90: 1 | G90: ls | H90: 129726.39 | I90: 0 | J90: Actual Costs to 9/23/26 | K90: H. Owner soft costs (engineering, siting, environmental, outreach, PM, land) | L90: =LEFT(K90,1) -> H
A91: Hyde Park BESS - Sta. 360 - Rev 3 | B91: 05 | C91: 05.02.02.00 | D91: 239 | E91: Engr. Station - Contractor | F91: 1050 | G91: mh | H91: 186895.55 | I91: 1050 | J91: Costs per email dated 9/18/26, Eng. Costs total $501,000 | K91: H. Owner soft costs (engineering, siting, environmental, outreach, PM, land) | L91: =LEFT(K91,1) -> H
A92: Hyde Park BESS - Sta. 360 - Rev 3 | B92: 05 | C92: 05.02.02.00 | D92: 440 | E92: Engr. Station - Contractor | F92: 1 | G92: ls | H92: 24652.8 | I92: 0 | J92: Actual Costs to 9/23/26 | K92: H. Owner soft costs (engineering, siting, environmental, outreach, PM, land) | L92: =LEFT(K92,1) -> H
A93: Hyde Park BESS - Sta. 360 - Rev 3 | B93: 05 | C93: 05.03.01.00 | D93: 442 | E93: Engr. Lines D AG - Eversource | F93: 1 | G93: ls | H93: 127849.97 | I93: 0 | J93: Actual Costs to 9/23/26 | K93: H. Owner soft costs (engineering, siting, environmental, outreach, PM, land) | L93: =LEFT(K93,1) -> H
A94: Hyde Park BESS - Sta. 360 - Rev 3 | B94: 05 | C94: 05.04.01.00 | D94: 242 | E94: Engr. P&C - Eversource | F94: 440 | G94: mh | H94: 29915.186 | I94: 440 | J94: Costs per email dated 9/18/26, Eng. Costs total $501,000 | K94: H. Owner soft costs (engineering, siting, environmental, outreach, PM, land) | L94: =LEFT(K94,1) -> H
A95: Hyde Park BESS - Sta. 360 - Rev 3 | B95: 05 | C95: 05.04.01.00 | D95: 443 | E95: Engr. P&C - Eversource | F95: 1 | G95: ls | H95: 69427.64 | I95: 0 | J95: Actual Costs to 9/23/26 | K95: H. Owner soft costs (engineering, siting, environmental, outreach, PM, land) | L95: =LEFT(K95,1) -> H
A96: Hyde Park BESS - Sta. 360 - Rev 3 | B96: 05 | C96: 05.04.02.00 | D96: 243 | E96: Engr. P&C - Contractor | F96: 900 | G96: mh | H96: 162181.22 | I96: 900 | J96: Costs per email dated 9/18/26, Eng. Costs total $501,000 | K96: H. Owner soft costs (engineering, siting, environmental, outreach, PM, land) | L96: =LEFT(K96,1) -> H
A97: Hyde Park BESS - Sta. 360 - Rev 3 | B97: 05 | C97: 05.05.01.00 | D97: 126 | E97: Engr. SCADA - Eversource | F97: 120 | G97: mh | H97: 8729.3094 | I97: 120 | J97: Mhrs from E-23-373 estimate | K97: H. Owner soft costs (engineering, siting, environmental, outreach, PM, land) | L97: =LEFT(K97,1) -> H
... A113: Hyde Park BESS - Sta. 360 - Rev 3 | B113: 06 | C113: 06.02.99.00 | D113: 478 | E113: AC/ DC Distribution Panels, Aux. Power Systems, (Furnish) | F113: 1 | G113: ea | H113: 67724.513 | I113: 0 | J113: Cost $56,030, Bidder lists dated 7/28/23. Add 3% per year inflation = $61,225 | K113: C. Battery balance-of-plant (GSUs, EMS/comms, aux power) | L113: =LEFT(K113,1) -> C
A114: Hyde Park BESS - Sta. 360 - Rev 3 | B114: 06 | C114: 06.02.99.00 | D114: 419 | E114: Automatic Transfer Switch, 400 amps, 3 Phase, (Furnish) | F114: 2 | G114: ea | H114: 21503.536 | I114: 0 | K114: D. Station 360 13.8 kV switching & interconnection facilities | L114: =LEFT(K114,1) -> D
A115: Hyde Park BESS - Sta. 360 - Rev 3 | B115: 06 | C115: 06.02.99.00 | D115: 428 | E115: Fuse Cutouts, 15 KV, 1 Phase, (Furnish) | F115: 33 | G115: ea | H115: 8266.4503 | I115: 0 | J115: Cost on line - Per estimator for three SSVTs (9) and PTs (24) Total 33. | K115: D. Station 360 13.8 kV switching & interconnection facilities | L115: =LEFT(K115,1) -> D
A116: Hyde Park BESS - Sta. 360 - Rev 3 | B116: 06 | C116: 06.02.99.00 | D116: 472 | E116: Insulators - 15kV, Dead-End Insulators, (Furnish) | F116: 12 | G116: ea | H116: 1592.8545 | I116: 0 | J116: OH cable from breaker to wood pole | K116: D. Station 360 13.8 kV switching & interconnection facilities | L116: =LEFT(K116,1) -> D
A117: Hyde Park BESS - Sta. 360 - Rev 3 | B117: 06 | C117: 06.02.99.00 | D117: 445 | E117: Misc. Eqt & Construction, Material (Furnish) | F117: 1 | G117: ls | H117: 1213042 | I117: 0 | J117: Actual Costs to 9/23/26 | K117: A. Battery supply contract (Nomad) | L117: =LEFT(K117,1) -> A
A118: Hyde Park BESS - Sta. 360 - Rev 3 | B118: 06 | C118: 06.02.99.00 | D118: 320 | E118: Wood Poles Distribution Wood Poles - 45ft, (Furnish) | F118: 8 | G118: ea | H118: 21238.06 | I118: 0 | K118: D. Station 360 13.8 kV switching & interconnection facilities | L118: =LEFT(K118,1) -> D
A119: Hyde Park BESS - Sta. 360 - Rev 3 | B119: 06 | C119: 06.03.02.00 | D119: 470 | E119: Cable Single Phase/Bare Cable 556 mcm ACSR, (26/7) Dove, (Furnish) | F119: 250 | G119: lf | H119: 580.72821 | I119: 0 | J119: 25' x 6 conductors x 2 - OH cable from breaker to wood pole on each side of the breaker | K119: D. Station 360 13.8 kV switching & interconnection facilities | L119: =LEFT(K119,1) -> D
A120: Hyde Park BESS - Sta. 360 - Rev 3 | B120: 06 | C120: 06.04.02.00 | D120: 334 | E120: Outdoor Metering Transclosure, , (Furnish) | F120: 4 | G120: ea | H120: 152648.56 | I120: 0 | K120: D. Station 360 13.8 kV switching & interconnection facilities | L120: =LEFT(K120,1) -> D
...
